{"name":"C","variations":[{"positions":[3,2,0,0,0,3],"baseFret":1},{"positions":[3,5,5,4,3,3],"baseFret":1,"barre":{"fromString":2,"toString":3,"fret":5}},{"positions":[7,-1,5,7,8,-1],"baseFret":5},{"positions":[-1,-1,5,7,8,7],"baseFret":5},{"positions":[-1,10,9,7,8,7],"baseFret":7},{"positions":[10,-1,9,7,8,-1],"baseFret":7}]}
{"name":"C5","variations":[{"positions":[-1,-1,0,0,3,3],"baseFret":1,"barre":{"fromString":5,"toString":6,"fret":3}},{"positions":[3,5,5,-1,-1,-1],"baseFret":1,"barre":{"fromString":2,"toString":3,"fret":5}},{"positions":[-1,-1,5,7,8,-1],"baseFret":5}]}
{"name":"C6","variations":[{"positions":[3,2,0,0,0,0],"baseFret":1},{"positions":[-1,-1,5,4,3,0],"baseFret":1},{"positions":[3,5,-1,4,5,3],"baseFret":1}]}
{"name":"C7","variations":[{"positions":[3,2,0,0,0,1],"baseFret":1},{"positions":[3,-1,3,4,3,0],"baseFret":1},{"positions":[3,5,3,4,3,3],"baseFret":1,"barre":{"fromString":5,"toString":6,"fret":3}},{"positions":[-1,-1,5,7,6,7],"baseFret":5},{"positions":[7,-1,5,7,6,-1],"baseFret":5}]}
{"name":"Cmaj7","variations":[{"positions":[3,2,0,0,0,2],"baseFret":1},{"positions":[-1,-1,5,4,3,2],"baseFret":1},{"positions":[-1,-1,5,7,7,7],"baseFret":5,"barre":{"fromString":4,"toString":6,"fret":7}}]}
{"name":"C9","variations":[{"positions":[3,-1,0,2,0,1],"baseFret":1},{"positions":[3,-1,3,2,0,3],"baseFret":1},{"positions":[3,5,3,4,3,5],"baseFret":1},{"positions":[-1,10,9,10,10,10],"baseFret":9,"barre":{"fromString":4,"toString":6,"fret":10}}]}
{"name":"Cmaj9","variations":[{"positions":[3,-1,0,2,0,2],"baseFret":1},{"positions":[-1,10,7,7,7,7],"baseFret":7,"barre":{"fromString":3,"toString":6,"fret":7}}]}
{"name":"C11","variations":[{"positions":[3,2,0,2,1,1],"baseFret":1,"barre":{"fromString":5,"toString":6,"fret":1}},{"positions":[3,3,3,4,3,5],"baseFret":1,"barre":{"fromString":1,"toString":3,"fret":3}},{"positions":[-1,-1,5,5,6,7],"baseFret":5,"barre":{"fromString":3,"toString":4,"fret":5}},{"positions":[-1,10,9,10,8,8],"baseFret":8,"barre":{"fromString":5,"toString":6,"fret":8}}]}
{"name":"C13","variations":[{"positions":[-1,-1,3,0,0,0],"baseFret":1},{"positions":[3,5,3,4,5,3],"baseFret":1},{"positions":[-1,-1,3,4,5,3],"baseFret":1}]}
{"name":"Cmaj13","variations":[{"positions":[3,2,2,2,3,2],"baseFret":1,"barre":{"fromString":2,"toString":4,"fret":2}},{"positions":[-1,10,-1,11,12,12],"baseFret":10,"barre":{"fromString":5,"toString":6,"fret":12}}]}
{"name":"Cm","variations":[{"positions":[3,1,0,0,3,3],"baseFret":1,"barre":{"fromString":5,"toString":6,"fret":3}},{"positions":[3,5,5,3,3,3],"baseFret":1,"barre":{"fromString":2,"toString":3,"fret":5}},{"positions":[-1,-1,5,3,3,6],"baseFret":1,"barre":{"fromString":4,"toString":5,"fret":3}},{"positions":[-1,-1,5,7,8,6],"baseFret":5},{"positions":[-1,-1,8,7,8,6],"baseFret":6},{"positions":[-1,10,8,7,8,-1],"baseFret":7}]}
{"name":"Cm6","variations":[{"positions":[-1,-1,2,3,3,3],"baseFret":1,"barre":{"fromString":4,"toString":6,"fret":3}},{"positions":[3,5,5,3,5,3],"baseFret":1,"barre":{"fromString":2,"toString":3,"fret":5}},{"positions":[-1,7,8,7,8,-1],"baseFret":7}]}
{"name":"Cm7","variations":[{"positions":[-1,1,3,0,3,-1],"baseFret":1},{"positions":[3,-1,3,3,3,-1],"baseFret":1,"barre":{"fromString":3,"toString":5,"fret":3}},{"positions":[3,5,3,3,6,3],"baseFret":1,"barre":{"fromString":3,"toString":4,"fret":3}},{"positions":[-1,10,-1,10,11,10],"baseFret":10}]}
{"name":"Cm9","variations":[{"positions":[3,-1,3,3,3,5],"baseFret":1,"barre":{"fromString":3,"toString":5,"fret":3}},{"positions":[-1,10,8,10,10,-1],"baseFret":8,"barre":{"fromString":4,"toString":5,"fret":10}}]}
{"name":"Cm11","variations":[{"positions":[3,3,3,3,3,3],"baseFret":1,"barre":{"fromString":1,"toString":6,"fret":3}},{"positions":[-1,10,10,10,11,10],"baseFret":10,"barre":{"fromString":2,"toString":4,"fret":10}}]}
{"name":"Cm13","variations":[{"positions":[3,5,3,3,5,3],"baseFret":1,"barre":{"fromString":3,"toString":4,"fret":3}},{"positions":[-1,10,-1,10,11,12],"baseFret":10}]}
{"name":"Cm(maj7)","variations":[{"positions":[3,5,4,3,3,3],"baseFret":1,"barre":{"fromString":4,"toString":6,"fret":3}},{"positions":[-1,10,8,7,7,-1],"baseFret":7,"barre":{"fromString":4,"toString":5,"fret":7}}]}
{"name":"Csus2","variations":[{"positions":[3,0,0,2,3,3],"baseFret":1,"barre":{"fromString":5,"toString":6,"fret":3}},{"positions":[-1,-1,5,7,8,5],"baseFret":5},{"positions":[-1,10,7,7,8,-1],"baseFret":7,"barre":{"fromString":3,"toString":4,"fret":7}}]}
{"name":"Csus4","variations":[{"positions":[3,5,5,5,3,3],"baseFret":1,"barre":{"fromString":2,"toString":4,"fret":5}},{"positions":[-1,-1,10,7,8,10],"baseFret":7}]}
{"name":"Cdim","variations":[{"positions":[3,-1,2,3,2,-1],"baseFret":1},{"positions":[-1,-1,5,6,5,6],"baseFret":5}]}
{"name":"Caug","variations":[{"positions":[3,2,1,0,0,3],"baseFret":1},{"positions":[3,-1,5,4,4,-1],"baseFret":1,"barre":{"fromString":4,"toString":5,"fret":4}},{"positions":[-1,6,-1,8,8,7],"baseFret":6,"barre":{"fromString":4,"toString":5,"fret":8}},{"positions":[-1,10,9,8,8,-1],"baseFret":8,"barre":{"fromString":4,"toString":5,"fret":8}}]}
{"name":"C6/9","variations":[{"positions":[3,2,2,2,3,3],"baseFret":1,"barre":{"fromString":2,"toString":4,"fret":2}},{"positions":[3,5,-1,4,5,5],"baseFret":1,"barre":{"fromString":5,"toString":6,"fret":5}},{"positions":[-1,5,5,4,5,5],"baseFret":4,"barre":{"fromString":2,"toString":3,"fret":5}},{"positions":[-1,7,7,7,8,7],"baseFret":7,"barre":{"fromString":2,"toString":4,"fret":7}}]}
{"name":"C7sus4","variations":[{"positions":[3,5,3,5,3,3],"baseFret":1,"barre":{"fromString":5,"toString":6,"fret":3}},{"positions":[-1,-1,5,7,6,8],"baseFret":5}]}
{"name":"C7b5","variations":[{"positions":[3,-1,3,4,2,-1],"baseFret":1},{"positions":[-1,-1,5,6,6,7],"baseFret":5,"barre":{"fromString":4,"toString":5,"fret":6}}]}
{"name":"C7b9","variations":[{"positions":[3,2,-1,1,3,1],"baseFret":1},{"positions":[3,5,6,4,3,3],"baseFret":1,"barre":{"fromString":5,"toString":6,"fret":3}},{"positions":[3,5,6,4,-1,-1],"baseFret":1},{"positions":[3,5,3,4,3,4],"baseFret":1},{"positions":[-1,-1,5,4,6,4],"baseFret":4},{"positions":[-1,10,9,10,9,-1],"baseFret":9},{"positions":[-1,10,9,10,9,10],"baseFret":9}]}
{"name":"C9sus4","variations":[{"positions":[3,-1,3,2,1,1],"baseFret":1,"barre":{"fromString":5,"toString":6,"fret":1}},{"positions":[-1,-1,5,5,6,5],"baseFret":5,"barre":{"fromString":3,"toString":4,"fret":5}},{"positions":[-1,10,-1,10,10,8],"baseFret":8,"barre":{"fromString":4,"toString":5,"fret":10}},{"positions":[-1,10,10,10,10,10],"baseFret":10,"barre":{"fromString":2,"toString":6,"fret":10}}]}
{"name":"Cadd9","variations":[{"positions":[3,0,0,2,0,3],"baseFret":1},{"positions":[-1,-1,5,4,3,5],"baseFret":1},{"positions":[-1,-1,7,7,8,7],"baseFret":7,"barre":{"fromString":3,"toString":4,"fret":7}},{"positions":[-1,10,9,7,10,7],"baseFret":7}]}
{"name":"Caug9","variations":[{"positions":[3,-1,3,4,4,5],"baseFret":1,"barre":{"fromString":4,"toString":5,"fret":4}},{"positions":[-1,10,9,10,10,11],"baseFret":9,"barre":{"fromString":4,"toString":5,"fret":10}}]}
{"name":"C#","variations":[{"positions":[4,3,1,1,1,-1],"baseFret":1,"barre":{"fromString":3,"toString":5,"fret":1}},{"positions":[-1,-1,1,1,1,4],"baseFret":1,"barre":{"fromString":3,"toString":5,"fret":1}},{"positions":[4,6,6,5,4,4],"baseFret":4,"barre":{"fromString":2,"toString":3,"fret":6}},{"positions":[8,-1,6,7,8,-1],"baseFret":6},{"positions":[-1,-1,6,8,9,8],"baseFret":6},{"positions":[-1,11,10,8,9,-1],"baseFret":8},{"positions":[-1,-1,10,8,9,11],"baseFret":8}]}
{"name":"C#5","variations":[{"positions":[-1,-1,1,1,4,4],"baseFret":1,"barre":{"fromString":3,"toString":4,"fret":1}},{"positions":[4,6,6,-1,-1,-1],"baseFret":4,"barre":{"fromString":2,"toString":3,"fret":6}},{"positions":[-1,-1,6,8,9,-1],"baseFret":6}]}
{"name":"C#6","variations":[{"positions":[-1,-1,1,1,1,1],"baseFret":1,"barre":{"fromString":3,"toString":6,"fret":1}},{"positions":[4,6,-1,5,6,4],"baseFret":4},{"positions":[-1,-1,6,8,6,8],"baseFret":6}]}
{"name":"C#7","variations":[{"positions":[-1,-1,1,1,1,2],"baseFret":1,"barre":{"fromString":3,"toString":5,"fret":1}},{"positions":[4,6,4,5,4,4],"baseFret":4,"barre":{"fromString":5,"toString":6,"fret":4}},{"positions":[4,6,-1,5,7,-1],"baseFret":4},{"positions":[4,-1,4,5,4,-1],"baseFret":4},{"positions":[-1,-1,6,8,7,8],"baseFret":6}]}
{"name":"C#maj7","variations":[{"positions":[-1,-1,1,1,1,3],"baseFret":1,"barre":{"fromString":3,"toString":5,"fret":1}},{"positions":[-1,-1,6,5,4,3],"baseFret":1},{"positions":[4,6,5,5,4,4],"baseFret":4,"barre":{"fromString":3,"toString":4,"fret":5}},{"positions":[-1,11,10,8,8,8],"baseFret":8,"barre":{"fromString":4,"toString":6,"fret":8}}]}
{"name":"C#9","variations":[{"positions":[4,-1,4,3,1,-1],"baseFret":1},{"positions":[4,6,4,5,4,6],"baseFret":4},{"positions":[-1,-1,6,5,7,6],"baseFret":5},{"positions":[-1,11,10,11,11,11],"baseFret":10,"barre":{"fromString":4,"toString":6,"fret":11}}]}
{"name":"C#maj9","variations":[{"positions":[4,3,5,3,4,-1],"baseFret":1},{"positions":[-1,3,6,3,4,3],"baseFret":1}]}
{"name":"C#11","variations":[{"positions":[-1,3,1,1,2,2],"baseFret":1,"barre":{"fromString":3,"toString":4,"fret":1}},{"positions":[4,4,4,5,4,6],"baseFret":4,"barre":{"fromString":1,"toString":3,"fret":4}},{"positions":[-1,-1,6,6,7,8],"baseFret":6,"barre":{"fromString":3,"toString":4,"fret":6}},{"positions":[-1,11,10,11,9,9],"baseFret":9,"barre":{"fromString":5,"toString":6,"fret":9}}]}
{"name":"C#13","variations":[{"positions":[4,-1,4,3,1,1],"baseFret":1,"barre":{"fromString":5,"toString":6,"fret":1}},{"positions":[4,-1,4,5,6,-1],"baseFret":4},{"positions":[4,6,4,5,6,6],"baseFret":4,"barre":{"fromString":5,"toString":6,"fret":6}}]}
{"name":"C#maj13","variations":[{"positions":[4,3,3,3,4,3],"baseFret":1,"barre":{"fromString":2,"toString":4,"fret":3}},{"positions":[-1,11,-1,12,13,13],"baseFret":11,"barre":{"fromString":5,"toString":6,"fret":13}}]}
{"name":"C#m","variations":[{"positions":[-1,2,1,1,4,4],"baseFret":1,"barre":{"fromString":3,"toString":4,"fret":1}},{"positions":[4,6,6,4,4,4],"baseFret":4,"barre":{"fromString":2,"toString":3,"fret":6}},{"positions":[7,-1,6,4,4,4],"baseFret":4,"barre":{"fromString":4,"toString":6,"fret":4}},{"positions":[-1,-1,6,8,9,7],"baseFret":6},{"positions":[-1,-1,9,8,9,7],"baseFret":7},{"positions":[-1,11,9,8,9,-1],"baseFret":8}]}
{"name":"C#m6","variations":[{"positions":[4,-1,3,4,4,-1],"baseFret":1,"barre":{"fromString":4,"toString":5,"fret":4}},{"positions":[4,6,6,4,6,4],"baseFret":4,"barre":{"fromString":2,"toString":3,"fret":6}},{"positions":[-1,-1,6,8,6,7],"baseFret":6}]}
{"name":"C#m7","variations":[{"positions":[4,-1,4,4,4,-1],"baseFret":4,"barre":{"fromString":3,"toString":5,"fret":4}},{"positions":[4,6,4,4,7,4],"baseFret":4,"barre":{"fromString":3,"toString":4,"fret":4}},{"positions":[-1,11,9,8,7,-1],"baseFret":7},{"positions":[-1,11,13,11,12,11],"baseFret":11}]}
{"name":"C#m9","variations":[{"positions":[-1,2,4,3,4,4],"baseFret":1,"barre":{"fromString":5,"toString":6,"fret":4}},{"positions":[4,-1,4,4,4,6],"baseFret":4,"barre":{"fromString":3,"toString":5,"fret":4}}]}
{"name":"C#m11","variations":[{"positions":[4,4,4,4,4,4],"baseFret":4,"barre":{"fromString":1,"toString":6,"fret":4}},{"positions":[-1,11,11,11,12,11],"baseFret":11,"barre":{"fromString":2,"toString":4,"fret":11}}]}
{"name":"C#m13","variations":[{"positions":[4,-1,4,4,6,-1],"baseFret":4,"barre":{"fromString":3,"toString":4,"fret":4}}]}
{"name":"C#m(maj7)","variations":[{"positions":[4,6,5,4,4,4],"baseFret":4,"barre":{"fromString":4,"toString":6,"fret":4}},{"positions":[-1,-1,6,8,8,7],"baseFret":6,"barre":{"fromString":4,"toString":5,"fret":8}}]}
{"name":"C#sus2","variations":[{"positions":[-1,1,1,1,4,4],"baseFret":1,"barre":{"fromString":2,"toString":4,"fret":1}},{"positions":[-1,-1,6,8,9,6],"baseFret":6},{"positions":[-1,11,8,8,9,-1],"baseFret":8,"barre":{"fromString":3,"toString":4,"fret":8}}]}
{"name":"C#sus4","variations":[{"positions":[-1,-1,1,1,2,4],"baseFret":1,"barre":{"fromString":3,"toString":4,"fret":1}},{"positions":[4,6,6,6,4,4],"baseFret":4,"barre":{"fromString":2,"toString":4,"fret":6}},{"positions":[-1,-1,6,8,9,9],"baseFret":6,"barre":{"fromString":5,"toString":6,"fret":9}}]}
{"name":"C#dim","variations":[{"positions":[4,-1,3,4,3,-1],"baseFret":1},{"positions":[-1,-1,6,7,6,7],"baseFret":6}]}
{"name":"C#aug","variations":[{"positions":[0,3,2,1,1,0],"baseFret":1,"barre":{"fromString":4,"toString":5,"fret":1}},{"positions":[4,-1,6,5,5,-1],"baseFret":4,"barre":{"fromString":4,"toString":5,"fret":5}},{"positions":[-1,-1,10,9,9,8],"baseFret":8,"barre":{"fromString":4,"toString":5,"fret":9}},{"positions":[-1,11,10,9,9,-1],"baseFret":9,"barre":{"fromString":4,"toString":5,"fret":9}}]}
{"name":"C#6/9","variations":[{"positions":[4,3,3,3,4,-1],"baseFret":1,"barre":{"fromString":2,"toString":4,"fret":3}},{"positions":[4,6,-1,5,6,6],"baseFret":4,"barre":{"fromString":5,"toString":6,"fret":6}},{"positions":[-1,6,6,5,6,6],"baseFret":5,"barre":{"fromString":2,"toString":3,"fret":6}},{"positions":[-1,11,10,10,11,11],"baseFret":10,"barre":{"fromString":3,"toString":4,"fret":10}}]}
{"name":"C#7sus4","variations":[{"positions":[-1,-1,1,1,2,2],"baseFret":1,"barre":{"fromString":3,"toString":4,"fret":1}},{"positions":[4,6,4,6,4,4],"baseFret":4,"barre":{"fromString":5,"toString":6,"fret":4}}]}
{"name":"C#7b5","variations":[{"positions":[4,-1,4,5,3,-1],"baseFret":1},{"positions":[-1,-1,6,7,7,8],"baseFret":6,"barre":{"fromString":4,"toString":5,"fret":7}}]}
{"name":"C#7b9","variations":[{"positions":[4,3,-1,2,4,2],"baseFret":1},{"positions":[4,6,7,5,4,4],"baseFret":4,"barre":{"fromString":5,"toString":6,"fret":4}},{"positions":[-1,11,10,11,10,11],"baseFret":10},{"positions":[-1,11,10,11,10,-1],"baseFret":10}]}
{"name":"C#9sus4","variations":[{"positions":[4,-1,4,3,2,-1],"baseFret":1},{"positions":[-1,6,6,6,7,6],"baseFret":6,"barre":{"fromString":2,"toString":4,"fret":6}},{"positions":[-1,11,-1,11,11,9],"baseFret":9,"barre":{"fromString":4,"toString":5,"fret":11}},{"positions":[-1,11,11,11,11,11],"baseFret":11,"barre":{"fromString":2,"toString":6,"fret":11}}]}
{"name":"C#add9","variations":[{"positions":[4,3,1,3,1,-1],"baseFret":1},{"positions":[-1,-1,6,5,4,6],"baseFret":4},{"positions":[-1,-1,8,8,9,8],"baseFret":8,"barre":{"fromString":3,"toString":4,"fret":8}},{"positions":[-1,11,10,8,11,-1],"baseFret":8}]}
{"name":"C#aug9","variations":[{"positions":[4,3,4,3,5,-1],"baseFret":1},{"positions":[4,-1,4,5,5,6],"baseFret":4,"barre":{"fromString":4,"toString":5,"fret":5}}]}
{"name":"D","variations":[{"positions":[-1,0,2,2,2,0],"baseFret":1,"barre":{"fromString":3,"toString":5,"fret":2}},{"positions":[5,4,2,2,2,-1],"baseFret":1,"barre":{"fromString":3,"toString":5,"fret":2}},{"positions":[5,7,7,6,5,5],"baseFret":5,"barre":{"fromString":2,"toString":3,"fret":7}},{"positions":[9,-1,7,9,10,-1],"baseFret":7},{"positions":[-1,-1,7,9,10,9],"baseFret":7}]}
{"name":"D5","variations":[{"positions":[-1,0,2,2,-1,-1],"baseFret":1,"barre":{"fromString":3,"toString":4,"fret":2}},{"positions":[-1,0,2,2,5,5],"baseFret":1,"barre":{"fromString":3,"toString":4,"fret":2}},{"positions":[5,7,7,-1,-1,-1],"baseFret":5,"barre":{"fromString":2,"toString":3,"fret":7}},{"positions":[-1,-1,7,9,10,-1],"baseFret":7}]}
{"name":"D6","variations":[{"positions":[-1,0,2,2,2,2],"baseFret":1,"barre":{"fromString":3,"toString":6,"fret":2}},{"positions":[5,-1,4,6,2,-1],"baseFret":1},{"positions":[5,7,-1,6,7,5],"baseFret":5}]}
{"name":"D7","variations":[{"positions":[-1,0,2,0,2,0],"baseFret":1},{"positions":[-1,0,2,2,2,1],"baseFret":1,"barre":{"fromString":3,"toString":5,"fret":2}},{"positions":[5,7,5,6,5,5],"baseFret":5,"barre":{"fromString":5,"toString":6,"fret":5}},{"positions":[5,7,-1,6,8,-1],"baseFret":5},{"positions":[-1,-1,7,9,8,9],"baseFret":7},{"positions":[-1,10,-1,9,10,9],"baseFret":9}]}
{"name":"Dmaj7","variations":[{"positions":[-1,0,2,1,2,0],"baseFret":1},{"positions":[-1,0,2,2,2,4],"baseFret":1,"barre":{"fromString":3,"toString":5,"fret":2}},{"positions":[-1,-1,7,6,5,4],"baseFret":4}]}
{"name":"D9","variations":[{"positions":[-1,0,2,4,2,3],"baseFret":1},{"positions":[5,4,5,4,5,-1],"baseFret":4},{"positions":[5,7,5,6,5,7],"baseFret":5}]}
{"name":"Dmaj9","variations":[{"positions":[-1,0,2,4,2,4],"baseFret":1},{"positions":[5,-1,6,6,-1,7],"baseFret":5,"barre":{"fromString":3,"toString":4,"fret":6}}]}
{"name":"D11","variations":[{"positions":[-1,0,0,0,2,0],"baseFret":1},{"positions":[5,5,5,6,5,7],"baseFret":5,"barre":{"fromString":1,"toString":3,"fret":5}},{"positions":[-1,-1,7,7,8,9],"baseFret":7,"barre":{"fromString":3,"toString":4,"fret":7}}]}
{"name":"D13","variations":[{"positions":[-1,0,2,0,2,2],"baseFret":1,"barre":{"fromString":5,"toString":6,"fret":2}},{"positions":[-1,-1,5,2,2,2],"baseFret":1,"barre":{"fromString":4,"toString":6,"fret":2}},{"positions":[5,7,5,6,7,5],"baseFret":5}]}
{"name":"Dmaj13","variations":[{"positions":[-1,0,2,1,2,2],"baseFret":1,"barre":{"fromString":5,"toString":6,"fret":2}},{"positions":[5,4,4,4,5,4],"baseFret":4,"barre":{"fromString":2,"toString":4,"fret":4}}]}
{"name":"Dm","variations":[{"positions":[-1,0,2,2,1,0],"baseFret":1,"barre":{"fromString":3,"toString":4,"fret":2}},{"positions":[-1,3,2,2,5,-1],"baseFret":1,"barre":{"fromString":3,"toString":4,"fret":2}},{"positions":[5,7,7,5,5,5],"baseFret":5,"barre":{"fromString":2,"toString":3,"fret":7}},{"positions":[-1,-1,7,5,5,8],"baseFret":5,"barre":{"fromString":4,"toString":5,"fret":5}},{"positions":[-1,7,10,9,10,-1],"baseFret":7},{"positions":[-1,-1,7,9,10,8],"baseFret":7}]}
{"name":"Dm6","variations":[{"positions":[-1,0,2,2,1,2],"baseFret":1,"barre":{"fromString":3,"toString":4,"fret":2}},{"positions":[5,-1,4,5,5,5],"baseFret":4,"barre":{"fromString":4,"toString":6,"fret":5}},{"positions":[-1,-1,7,9,7,8],"baseFret":7}]}
{"name":"Dm7","variations":[{"positions":[-1,0,2,0,1,0],"baseFret":1},{"positions":[5,7,5,5,8,5],"baseFret":5,"barre":{"fromString":3,"toString":4,"fret":5}},{"positions":[5,-1,5,5,5,-1],"baseFret":5,"barre":{"fromString":3,"toString":5,"fret":5}}]}
{"name":"Dm9","variations":[{"positions":[5,3,2,0,0,0],"baseFret":1},{"positions":[-1,0,2,4,1,0],"baseFret":1},{"positions":[-1,0,5,5,0,0],"baseFret":1,"barre":{"fromString":3,"toString":4,"fret":5}},{"positions":[5,-1,5,5,5,7],"baseFret":5,"barre":{"fromString":3,"toString":5,"fret":5}}]}
{"name":"Dm11","variations":[{"positions":[-1,0,0,0,1,0],"baseFret":1},{"positions":[-1,7,7,7,8,8],"baseFret":7,"barre":{"fromString":2,"toString":4,"fret":7}}]}
{"name":"Dm13","variations":[{"positions":[-1,0,2,0,1,2],"baseFret":1},{"positions":[5,7,5,5,7,5],"baseFret":5,"barre":{"fromString":3,"toString":4,"fret":5}}]}
{"name":"Dm(maj7)","variations":[{"positions":[-1,0,2,2,1,4],"baseFret":1,"barre":{"fromString":3,"toString":4,"fret":2}},{"positions":[5,7,6,5,5,5],"baseFret":5,"barre":{"fromString":4,"toString":6,"fret":5}}]}
{"name":"Dsus2","variations":[{"positions":[-1,0,2,2,0,0],"baseFret":1,"barre":{"fromString":3,"toString":4,"fret":2}},{"positions":[5,-1,-1,4,5,5],"baseFret":4,"barre":{"fromString":5,"toString":6,"fret":5}},{"positions":[-1,-1,7,9,10,7],"baseFret":7}]}
{"name":"Dsus4","variations":[{"positions":[-1,0,2,2,3,0],"baseFret":1,"barre":{"fromString":3,"toString":4,"fret":2}},{"positions":[5,7,7,7,5,5],"baseFret":5,"barre":{"fromString":2,"toString":4,"fret":7}},{"positions":[-1,7,7,7,10,10],"baseFret":7,"barre":{"fromString":2,"toString":4,"fret":7}}]}
{"name":"Ddim","variations":[{"positions":[-1,0,1,2,1,2],"baseFret":1},{"positions":[5,-1,4,5,4,-1],"baseFret":4}]}
{"name":"Daug","variations":[{"positions":[-1,0,3,2,2,1],"baseFret":1,"barre":{"fromString":4,"toString":5,"fret":2}},{"positions":[5,-1,7,6,6,-1],"baseFret":5,"barre":{"fromString":4,"toString":5,"fret":6}},{"positions":[-1,-1,11,10,10,9],"baseFret":9,"barre":{"fromString":4,"toString":5,"fret":10}}]}
{"name":"D6/9","variations":[{"positions":[-1,0,4,4,2,0],"baseFret":1,"barre":{"fromString":3,"toString":4,"fret":4}},{"positions":[5,2,2,2,2,2],"baseFret":1,"barre":{"fromString":2,"toString":6,"fret":2}},{"positions":[5,7,-1,6,7,7],"baseFret":5,"barre":{"fromString":5,"toString":6,"fret":7}},{"positions":[-1,9,9,9,10,9],"baseFret":9,"barre":{"fromString":2,"toString":4,"fret":9}}]}
{"name":"D7sus4","variations":[{"positions":[-1,0,2,0,3,0],"baseFret":1},{"positions":[5,7,5,7,5,5],"baseFret":5,"barre":{"fromString":5,"toString":6,"fret":5}}]}
{"name":"D7b5","variations":[{"positions":[-1,0,1,2,2,3],"baseFret":1,"barre":{"fromString":4,"toString":5,"fret":2}},{"positions":[-1,6,7,6,8,-1],"baseFret":6}]}
{"name":"D7b9","variations":[{"positions":[5,4,-1,3,5,3],"baseFret":1},{"positions":[5,7,8,6,5,5],"baseFret":5,"barre":{"fromString":5,"toString":6,"fret":5}},{"positions":[5,7,5,6,5,6],"baseFret":5}]}
{"name":"D9sus4","variations":[{"positions":[5,-1,5,4,3,-1],"baseFret":1},{"positions":[-1,-1,7,7,8,7],"baseFret":7,"barre":{"fromString":3,"toString":4,"fret":7}}]}
{"name":"Dadd9","variations":[{"positions":[-1,0,2,4,2,0],"baseFret":1},{"positions":[-1,-1,7,6,5,7],"baseFret":5},{"positions":[-1,-1,9,9,10,9],"baseFret":9,"barre":{"fromString":3,"toString":4,"fret":9}}]}
{"name":"Daug9","variations":[{"positions":[5,-1,5,6,6,7],"baseFret":5,"barre":{"fromString":4,"toString":5,"fret":6}},{"positions":[-1,10,9,10,10,11],"baseFret":9,"barre":{"fromString":4,"toString":5,"fret":10}}]}
{"name":"Eb","variations":[{"positions":[-1,1,3,3,3,1],"baseFret":1,"barre":{"fromString":3,"toString":5,"fret":3}},{"positions":[6,5,3,3,3,-1],"baseFret":1,"barre":{"fromString":3,"toString":5,"fret":3}},{"positions":[-1,-1,3,3,3,6],"baseFret":1,"barre":{"fromString":3,"toString":5,"fret":3}},{"positions":[6,8,8,7,6,6],"baseFret":6,"barre":{"fromString":2,"toString":3,"fret":8}},{"positions":[10,-1,8,10,11,-1],"baseFret":8},{"positions":[-1,-1,8,10,11,10],"baseFret":8}]}
{"name":"Eb5","variations":[{"positions":[-1,1,3,3,-1,-1],"baseFret":1,"barre":{"fromString":3,"toString":4,"fret":3}},{"positions":[-1,-1,3,3,6,6],"baseFret":1,"barre":{"fromString":3,"toString":4,"fret":3}},{"positions":[6,8,8,-1,-1,-1],"baseFret":6,"barre":{"fromString":2,"toString":3,"fret":8}},{"positions":[-1,-1,8,10,11,-1],"baseFret":8}]}
{"name":"Eb6","variations":[{"positions":[-1,1,3,3,3,3],"baseFret":1,"barre":{"fromString":3,"toString":6,"fret":3}},{"positions":[6,5,3,3,3,3],"baseFret":1,"barre":{"fromString":3,"toString":6,"fret":3}},{"positions":[6,-1,5,7,6,-1],"baseFret":5},{"positions":[6,8,-1,7,8,6],"baseFret":6}]}
{"name":"Eb7","variations":[{"positions":[-1,1,3,1,3,1],"baseFret":1},{"positions":[4,-1,3,3,3,-1],"baseFret":1,"barre":{"fromString":3,"toString":5,"fret":3}},{"positions":[-1,1,3,3,3,4],"baseFret":1,"barre":{"fromString":3,"toString":5,"fret":3}},{"positions":[6,8,6,7,6,6],"baseFret":6,"barre":{"fromString":5,"toString":6,"fret":6}},{"positions":[6,8,-1,7,9,-1],"baseFret":6},{"positions":[-1,-1,8,10,9,10],"baseFret":8}]}
{"name":"Ebmaj7","variations":[{"positions":[-1,1,3,2,3,1],"baseFret":1},{"positions":[-1,-1,8,7,6,5],"baseFret":5},{"positions":[6,-1,7,7,6,-1],"baseFret":6,"barre":{"fromString":3,"toString":4,"fret":7}},{"positions":[-1,-1,8,10,10,10],"baseFret":8,"barre":{"fromString":4,"toString":6,"fret":10}}]}
{"name":"Eb9","variations":[{"positions":[-1,1,0,1,1,1],"baseFret":1,"barre":{"fromString":4,"toString":6,"fret":1}},{"positions":[6,-1,6,5,3,-1],"baseFret":1},{"positions":[6,8,6,7,6,8],"baseFret":6},{"positions":[10,-1,8,10,9,8],"baseFret":8}]}
{"name":"Ebmaj9","variations":[{"positions":[-1,1,0,2,1,1],"baseFret":1,"barre":{"fromString":5,"toString":6,"fret":1}},{"positions":[6,-1,7,7,-1,8],"baseFret":6,"barre":{"fromString":3,"toString":4,"fret":7}}]}
{"name":"Eb11","variations":[{"positions":[-1,1,1,1,3,1],"baseFret":1,"barre":{"fromString":2,"toString":4,"fret":1}},{"positions":[6,6,6,7,6,8],"baseFret":6,"barre":{"fromString":1,"toString":3,"fret":6}},{"positions":[-1,-1,8,8,9,10],"baseFret":8,"barre":{"fromString":3,"toString":4,"fret":8}},{"positions":[10,-1,-1,10,9,11],"baseFret":9}]}
{"name":"Eb13","variations":[{"positions":[-1,1,-1,1,3,3],"baseFret":1,"barre":{"fromString":5,"toString":6,"fret":3}},{"positions":[6,8,6,7,8,6],"baseFret":6},{"positions":[6,-1,6,7,8,8],"baseFret":6,"barre":{"fromString":5,"toString":6,"fret":8}}]}
{"name":"Ebmaj13","variations":[{"positions":[-1,1,-1,2,3,3],"baseFret":1,"barre":{"fromString":5,"toString":6,"fret":3}},{"positions":[6,-1,7,7,8,8],"baseFret":6,"barre":{"fromString":3,"toString":4,"fret":7}}]}
{"name":"Ebm","variations":[{"positions":[-1,1,3,3,2,1],"baseFret":1,"barre":{"fromString":3,"toString":4,"fret":3}},{"positions":[-1,-1,3,6,6,6],"baseFret":1,"barre":{"fromString":4,"toString":6,"fret":6}},{"positions":[-1,4,3,3,6,-1],"baseFret":1,"barre":{"fromString":3,"toString":4,"fret":3}},{"positions":[6,8,8,6,6,6],"baseFret":6,"barre":{"fromString":2,"toString":3,"fret":8}},{"positions":[-1,-1,8,6,6,9],"baseFret":6,"barre":{"fromString":4,"toString":5,"fret":6}},{"positions":[-1,-1,8,10,11,9],"baseFret":8},{"positions":[-1,13,11,10,11,-1],"baseFret":10}]}
{"name":"Ebm6","variations":[{"positions":[-1,1,3,0,2,-1],"baseFret":1},{"positions":[6,-1,5,6,6,-1],"baseFret":5,"barre":{"fromString":4,"toString":5,"fret":6}},{"positions":[6,8,8,6,8,6],"baseFret":6,"barre":{"fromString":2,"toString":3,"fret":8}}]}
{"name":"Ebm7","variations":[{"positions":[-1,1,3,1,2,1],"baseFret":1},{"positions":[6,8,6,6,9,6],"baseFret":6,"barre":{"fromString":3,"toString":4,"fret":6}},{"positions":[6,-1,6,6,6,-1],"baseFret":6,"barre":{"fromString":3,"toString":5,"fret":6}},{"positions":[-1,-1,8,10,9,9],"baseFret":8,"barre":{"fromString":5,"toString":6,"fret":9}}]}
{"name":"Ebm9","variations":[{"positions":[6,-1,6,6,6,8],"baseFret":6,"barre":{"fromString":3,"toString":5,"fret":6}},{"positions":[-1,13,11,13,13,-1],"baseFret":11,"barre":{"fromString":4,"toString":5,"fret":13}}]}
{"name":"Ebm11","variations":[{"positions":[-1,1,1,1,2,1],"baseFret":1,"barre":{"fromString":2,"toString":4,"fret":1}},{"positions":[-1,8,8,8,9,9],"baseFret":8,"barre":{"fromString":2,"toString":4,"fret":8}}]}
{"name":"Ebm13","variations":[{"positions":[-1,1,-1,1,2,3],"baseFret":1},{"positions":[6,8,6,6,8,6],"baseFret":6,"barre":{"fromString":3,"toString":4,"fret":6}}]}
{"name":"Ebm(maj7)","variations":[{"positions":[-1,1,3,2,2,1],"baseFret":1,"barre":{"fromString":4,"toString":5,"fret":2}},{"positions":[-1,-1,8,10,10,9],"baseFret":8,"barre":{"fromString":4,"toString":5,"fret":10}}]}
{"name":"Ebsus2","variations":[{"positions":[-1,1,3,3,1,1],"baseFret":1,"barre":{"fromString":3,"toString":4,"fret":3}},{"positions":[6,-1,-1,5,6,6],"baseFret":5,"barre":{"fromString":5,"toString":6,"fret":6}},{"positions":[-1,-1,8,10,11,8],"baseFret":8},{"positions":[-1,13,10,10,11,-1],"baseFret":10,"barre":{"fromString":3,"toString":4,"fret":10}}]}
{"name":"Ebsus4","variations":[{"positions":[-1,1,1,3,4,1],"baseFret":1,"barre":{"fromString":2,"toString":3,"fret":1}},{"positions":[6,8,8,8,6,6],"baseFret":6,"barre":{"fromString":2,"toString":4,"fret":8}},{"positions":[-1,8,8,8,11,11],"baseFret":8,"barre":{"fromString":2,"toString":4,"fret":8}}]}
{"name":"Ebdim","variations":[{"positions":[6,-1,5,6,5,-1],"baseFret":5},{"positions":[6,7,8,6,8,6],"baseFret":6}]}
{"name":"Ebaug","variations":[{"positions":[-1,1,0,3,3,2],"baseFret":1,"barre":{"fromString":4,"toString":5,"fret":3}},{"positions":[6,-1,8,7,7,-1],"baseFret":6,"barre":{"fromString":4,"toString":5,"fret":7}},{"positions":[-1,-1,8,7,7,6],"baseFret":6,"barre":{"fromString":4,"toString":5,"fret":7}},{"positions":[-1,-1,8,7,7,10],"baseFret":7,"barre":{"fromString":4,"toString":5,"fret":7}}]}
{"name":"Eb6/9","variations":[{"positions":[-1,1,0,0,1,1],"baseFret":1,"barre":{"fromString":5,"toString":6,"fret":1}},{"positions":[6,3,3,3,3,3],"baseFret":1,"barre":{"fromString":2,"toString":6,"fret":3}},{"positions":[-1,5,5,5,6,6],"baseFret":5,"barre":{"fromString":2,"toString":4,"fret":5}},{"positions":[-1,10,10,10,11,10],"baseFret":10,"barre":{"fromString":2,"toString":4,"fret":10}}]}
{"name":"Eb7sus4","variations":[{"positions":[-1,1,3,1,4,1],"baseFret":1},{"positions":[-1,-1,8,10,9,11],"baseFret":8}]}
{"name":"Eb7b5","variations":[{"positions":[-1,1,0,1,3,0],"baseFret":1},{"positions":[-1,-1,8,9,9,10],"baseFret":8,"barre":{"fromString":4,"toString":5,"fret":9}}]}
{"name":"Eb7b9","variations":[{"positions":[-1,1,0,1,0,1],"baseFret":1},{"positions":[6,5,-1,4,6,4],"baseFret":4},{"positions":[6,8,9,7,6,6],"baseFret":6,"barre":{"fromString":5,"toString":6,"fret":6}},{"positions":[6,8,9,7,-1,-1],"baseFret":6},{"positions":[6,8,6,7,6,7],"baseFret":6}]}
{"name":"Eb9sus4","variations":[{"positions":[-1,1,1,1,1,1],"baseFret":1,"barre":{"fromString":2,"toString":6,"fret":1}},{"positions":[6,-1,6,5,4,-1],"baseFret":4},{"positions":[6,8,6,8,6,8],"baseFret":6}]}
{"name":"Ebadd9","variations":[{"positions":[-1,1,1,1,1,-1],"baseFret":1,"barre":{"fromString":2,"toString":5,"fret":1}},{"positions":[-1,1,3,5,3,1],"baseFret":1},{"positions":[-1,-1,8,7,6,8],"baseFret":6},{"positions":[-1,-1,10,10,11,10],"baseFret":10,"barre":{"fromString":3,"toString":4,"fret":10}}]}
{"name":"Ebaug9","variations":[{"positions":[-1,1,0,1,1,2],"baseFret":1,"barre":{"fromString":4,"toString":5,"fret":1}},{"positions":[6,-1,6,7,7,8],"baseFret":6,"barre":{"fromString":4,"toString":5,"fret":7}}]}
{"name":"E","variations":[{"positions":[-1,2,4,4,4,2],"baseFret":1,"barre":{"fromString":3,"toString":5,"fret":4}},{"positions":[7,6,4,4,4,-1],"baseFret":4,"barre":{"fromString":3,"toString":5,"fret":4}},{"positions":[-1,-1,4,4,4,7],"baseFret":4,"barre":{"fromString":3,"toString":5,"fret":4}},{"positions":[7,9,9,8,7,7],"baseFret":7,"barre":{"fromString":2,"toString":3,"fret":9}}]}
{"name":"E5","variations":[{"positions":[-1,2,4,4,-1,-1],"baseFret":1,"barre":{"fromString":3,"toString":4,"fret":4}},{"positions":[-1,-1,4,4,7,7],"baseFret":4,"barre":{"fromString":3,"toString":4,"fret":4}},{"positions":[7,9,9,-1,-1,-1],"baseFret":7,"barre":{"fromString":2,"toString":3,"fret":9}}]}
{"name":"E6","variations":[{"positions":[2,2,1,1,0,-1],"baseFret":1,"barre":{"fromString":1,"toString":2,"fret":2}},{"positions":[-1,2,4,4,4,4],"baseFret":1,"barre":{"fromString":3,"toString":6,"fret":4}},{"positions":[7,-1,6,8,7,-1],"baseFret":6},{"positions":[7,9,-1,8,9,7],"baseFret":7}]}
{"name":"E7","variations":[{"positions":[-1,2,1,2,0,2],"baseFret":1},{"positions":[-1,2,4,4,4,5],"baseFret":1,"barre":{"fromString":3,"toString":5,"fret":4}},{"positions":[-1,2,4,2,4,2],"baseFret":1},{"positions":[7,9,7,8,7,7],"baseFret":7,"barre":{"fromString":5,"toString":6,"fret":7}},{"positions":[7,9,7,8,10,7],"baseFret":7},{"positions":[-1,-1,9,11,10,11],"baseFret":9}]}
{"name":"Emaj7","variations":[{"positions":[2,2,1,3,0,-1],"baseFret":1,"barre":{"fromString":1,"toString":2,"fret":2}},{"positions":[-1,2,4,3,4,2],"baseFret":1},{"positions":[-1,-1,9,8,7,6],"baseFret":6},{"positions":[7,-1,8,8,7,-1],"baseFret":7,"barre":{"fromString":3,"toString":4,"fret":8}}]}
{"name":"E9","variations":[{"positions":[-1,2,1,2,2,2],"baseFret":1,"barre":{"fromString":4,"toString":6,"fret":2}},{"positions":[7,-1,7,6,4,-1],"baseFret":4},{"positions":[7,6,7,6,-1,-1],"baseFret":6},{"positions":[7,9,7,8,7,9],"baseFret":7}]}
{"name":"Emaj9","variations":[{"positions":[-1,2,1,3,2,2],"baseFret":1,"barre":{"fromString":5,"toString":6,"fret":2}},{"positions":[7,-1,8,8,-1,9],"baseFret":7,"barre":{"fromString":3,"toString":4,"fret":8}}]}
{"name":"E11","variations":[{"positions":[-1,2,1,2,2,0],"baseFret":1,"barre":{"fromString":4,"toString":5,"fret":2}},{"positions":[-1,1,1,1,3,1],"baseFret":1,"barre":{"fromString":2,"toString":4,"fret":1}},{"positions":[7,7,7,8,7,9],"baseFret":7,"barre":{"fromString":1,"toString":3,"fret":7}},{"positions":[-1,-1,9,9,10,11],"baseFret":9,"barre":{"fromString":3,"toString":4,"fret":9}}]}
{"name":"E13","variations":[{"positions":[-1,2,1,2,2,4],"baseFret":1,"barre":{"fromString":4,"toString":5,"fret":2}},{"positions":[-1,2,-1,2,4,4],"baseFret":1,"barre":{"fromString":5,"toString":6,"fret":4}},{"positions":[7,-1,7,8,9,-1],"baseFret":7}]}
{"name":"Emaj13","variations":[{"positions":[-1,2,-1,3,4,4],"baseFret":1,"barre":{"fromString":5,"toString":6,"fret":4}},{"positions":[7,-1,8,8,9,-1],"baseFret":7,"barre":{"fromString":3,"toString":4,"fret":8}}]}
{"name":"Em","variations":[{"positions":[-1,2,4,4,3,2],"baseFret":1,"barre":{"fromString":3,"toString":4,"fret":4}},{"positions":[-1,5,4,4,3,-1],"baseFret":1,"barre":{"fromString":3,"toString":4,"fret":4}},{"positions":[-1,5,4,4,7,-1],"baseFret":4,"barre":{"fromString":3,"toString":4,"fret":4}},{"positions":[7,9,9,7,7,7],"baseFret":7,"barre":{"fromString":2,"toString":3,"fret":9}}]}
{"name":"Em6","variations":[{"positions":[-1,2,-1,1,3,2],"baseFret":1},{"positions":[-1,2,4,-1,3,4],"baseFret":1},{"positions":[7,-1,6,7,7,7],"baseFret":6,"barre":{"fromString":4,"toString":6,"fret":7}},{"positions":[7,9,9,7,9,7],"baseFret":7,"barre":{"fromString":2,"toString":3,"fret":9}}]}
{"name":"Em7","variations":[{"positions":[-1,2,0,2,0,2],"baseFret":1},{"positions":[-1,2,4,2,3,2],"baseFret":1},{"positions":[7,-1,7,7,7,-1],"baseFret":7,"barre":{"fromString":3,"toString":5,"fret":7}},{"positions":[7,9,7,7,10,7],"baseFret":7,"barre":{"fromString":3,"toString":4,"fret":7}}]}
{"name":"Em9","variations":[{"positions":[-1,2,0,2,2,2],"baseFret":1,"barre":{"fromString":4,"toString":6,"fret":2}},{"positions":[7,-1,7,7,7,10],"baseFret":7,"barre":{"fromString":3,"toString":5,"fret":7}}]}
{"name":"Em11","variations":[{"positions":[-1,2,2,2,3,2],"baseFret":1,"barre":{"fromString":2,"toString":4,"fret":2}},{"positions":[7,7,7,7,7,7],"baseFret":7,"barre":{"fromString":1,"toString":6,"fret":7}}]}
{"name":"Em13","variations":[{"positions":[-1,2,-1,2,3,4],"baseFret":1},{"positions":[7,9,7,7,9,7],"baseFret":7,"barre":{"fromString":3,"toString":4,"fret":7}}]}
{"name":"Em(maj7)","variations":[{"positions":[-1,2,-1,3,3,2],"baseFret":1,"barre":{"fromString":4,"toString":5,"fret":3}},{"positions":[7,9,8,7,7,7],"baseFret":7,"barre":{"fromString":4,"toString":6,"fret":7}}]}
{"name":"Esus2","variations":[{"positions":[-1,2,4,4,2,2],"baseFret":1,"barre":{"fromString":3,"toString":4,"fret":4}},{"positions":[7,-1,-1,6,7,7],"baseFret":6,"barre":{"fromString":5,"toString":6,"fret":7}}]}
{"name":"Esus4","variations":[{"positions":[-1,2,4,4,5,2],"baseFret":1,"barre":{"fromString":3,"toString":4,"fret":4}},{"positions":[7,9,9,9,7,7],"baseFret":7,"barre":{"fromString":2,"toString":4,"fret":9}},{"positions":[-1,-1,9,9,7,7],"baseFret":7,"barre":{"fromString":3,"toString":4,"fret":9}}]}
{"name":"Edim","variations":[{"positions":[-1,2,3,1,3,-1],"baseFret":1},{"positions":[7,8,9,7,9,7],"baseFret":7}]}
{"name":"Eaug","variations":[{"positions":[-1,2,1,0,0,3],"baseFret":1},{"positions":[7,-1,9,8,8,-1],"baseFret":7,"barre":{"fromString":4,"toString":5,"fret":8}},{"positions":[-1,-1,9,8,8,7],"baseFret":7,"barre":{"fromString":4,"toString":5,"fret":8}},{"positions":[-1,-1,9,8,8,11],"baseFret":8,"barre":{"fromString":4,"toString":5,"fret":8}}]}
{"name":"E6/9","variations":[{"positions":[-1,2,1,1,2,2],"baseFret":1,"barre":{"fromString":3,"toString":4,"fret":1}},{"positions":[7,4,4,4,4,4],"baseFret":4,"barre":{"fromString":2,"toString":6,"fret":4}},{"positions":[7,6,6,6,7,-1],"baseFret":6,"barre":{"fromString":2,"toString":4,"fret":6}},{"positions":[7,9,-1,8,9,9],"baseFret":7,"barre":{"fromString":5,"toString":6,"fret":9}}]}
{"name":"E7sus4","variations":[{"positions":[-1,2,4,2,5,2],"baseFret":1},{"positions":[7,9,7,9,7,7],"baseFret":7,"barre":{"fromString":5,"toString":6,"fret":7}}]}
{"name":"E7b5","variations":[{"positions":[-1,2,3,2,4,-1],"baseFret":1},{"positions":[7,8,7,8,-1,-1],"baseFret":7}]}
{"name":"E7b9","variations":[{"positions":[-1,2,1,2,1,2],"baseFret":1},{"positions":[7,6,-1,5,7,5],"baseFret":5},{"positions":[7,9,10,8,7,7],"baseFret":7,"barre":{"fromString":5,"toString":6,"fret":7}},{"positions":[7,9,7,8,7,8],"baseFret":7}]}
{"name":"E9sus4","variations":[{"positions":[-1,2,2,2,2,2],"baseFret":1,"barre":{"fromString":2,"toString":6,"fret":2}},{"positions":[7,-1,7,6,5,-1],"baseFret":5},{"positions":[-1,9,9,9,10,9],"baseFret":9,"barre":{"fromString":2,"toString":4,"fret":9}}]}
{"name":"Eadd9","variations":[{"positions":[-1,4,4,4,4,-1],"baseFret":4,"barre":{"fromString":2,"toString":5,"fret":4}},{"positions":[-1,2,4,6,4,2],"baseFret":1},{"positions":[-1,-1,9,8,7,9],"baseFret":7}]}
{"name":"Eaug9","variations":[{"positions":[-1,2,1,2,2,3],"baseFret":1,"barre":{"fromString":4,"toString":5,"fret":2}},{"positions":[7,-1,7,8,8,9],"baseFret":7,"barre":{"fromString":4,"toString":5,"fret":8}}]}
{"name":"F","variations":[{"positions":[-1,3,2,0,1,0],"baseFret":1},{"positions":[3,3,2,0,1,0],"baseFret":1,"barre":{"fromString":1,"toString":2,"fret":3}},{"positions":[3,3,5,5,5,3],"baseFret":1,"barre":{"fromString":1,"toString":2,"fret":3}},{"positions":[8,7,5,5,5,-1],"baseFret":5,"barre":{"fromString":3,"toString":5,"fret":5}},{"positions":[-1,-1,5,5,5,8],"baseFret":5,"barre":{"fromString":3,"toString":5,"fret":5}},{"positions":[8,10,10,9,8,8],"baseFret":8,"barre":{"fromString":2,"toString":3,"fret":10}}]}
{"name":"F5","variations":[{"positions":[-1,3,5,5,-1,-1],"baseFret":1,"barre":{"fromString":3,"toString":4,"fret":5}},{"positions":[-1,-1,5,5,8,8],"baseFret":5,"barre":{"fromString":3,"toString":4,"fret":5}},{"positions":[8,10,10,-1,-1,-1],"baseFret":8,"barre":{"fromString":2,"toString":3,"fret":10}}]}
{"name":"F6","variations":[{"positions":[3,-1,2,2,1,-1],"baseFret":1,"barre":{"fromString":3,"toString":4,"fret":2}},{"positions":[-1,3,5,5,5,5],"baseFret":1,"barre":{"fromString":3,"toString":6,"fret":5}},{"positions":[8,-1,7,9,8,-1],"baseFret":7},{"positions":[8,10,-1,9,10,8],"baseFret":8}]}
{"name":"F7","variations":[{"positions":[-1,3,2,3,1,0],"baseFret":1},{"positions":[-1,3,5,3,5,3],"baseFret":1},{"positions":[8,10,-1,9,11,-1],"baseFret":8},{"positions":[8,10,8,9,8,8],"baseFret":8,"barre":{"fromString":5,"toString":6,"fret":8}}]}
{"name":"Fmaj7","variations":[{"positions":[-1,3,2,0,0,0],"baseFret":1},{"positions":[-1,3,5,4,5,3],"baseFret":1},{"positions":[-1,-1,10,9,8,7],"baseFret":7}]}
{"name":"F9","variations":[{"positions":[-1,3,2,3,3,3],"baseFret":1,"barre":{"fromString":4,"toString":6,"fret":3}},{"positions":[8,-1,8,7,5,-1],"baseFret":5},{"positions":[8,10,8,9,8,10],"baseFret":8},{"positions":[-1,-1,10,9,11,10],"baseFret":9}]}
{"name":"Fmaj9","variations":[{"positions":[-1,3,5,4,3,0],"baseFret":1},{"positions":[-1,7,10,7,8,7],"baseFret":7}]}
{"name":"F11","variations":[{"positions":[-1,3,2,3,1,1],"baseFret":1,"barre":{"fromString":5,"toString":6,"fret":1}},{"positions":[-1,3,3,3,5,3],"baseFret":1,"barre":{"fromString":2,"toString":4,"fret":3}},{"positions":[-1,7,-1,5,6,6],"baseFret":5,"barre":{"fromString":5,"toString":6,"fret":6}}]}
{"name":"F13","variations":[{"positions":[-1,1,2,2,1,-1],"baseFret":1,"barre":{"fromString":3,"toString":4,"fret":2}},{"positions":[8,-1,8,7,5,5],"baseFret":5,"barre":{"fromString":5,"toString":6,"fret":5}},{"positions":[-1,-1,8,9,10,7],"baseFret":7},{"positions":[8,-1,8,9,10,-1],"baseFret":8}]}
{"name":"Fmaj13","variations":[{"positions":[-1,3,-1,4,5,5],"baseFret":1,"barre":{"fromString":5,"toString":6,"fret":5}},{"positions":[8,7,7,7,8,7],"baseFret":7,"barre":{"fromString":2,"toString":4,"fret":7}}]}
{"name":"Fm","variations":[{"positions":[-1,3,1,0,1,-1],"baseFret":1},{"positions":[-1,3,5,5,4,3],"baseFret":1,"barre":{"fromString":3,"toString":4,"fret":5}},{"positions":[-1,6,5,5,4,-1],"baseFret":4,"barre":{"fromString":3,"toString":4,"fret":5}},{"positions":[-1,-1,5,8,8,8],"baseFret":5,"barre":{"fromString":4,"toString":6,"fret":8}},{"positions":[-1,6,5,5,8,-1],"baseFret":5,"barre":{"fromString":3,"toString":4,"fret":5}},{"positions":[8,10,10,8,8,8],"baseFret":8,"barre":{"fromString":2,"toString":3,"fret":10}}]}
{"name":"Fm6","variations":[{"positions":[-1,0,1,0,1,3],"baseFret":1},{"positions":[-1,3,-1,2,4,3],"baseFret":1},{"positions":[8,-1,7,8,8,-1],"baseFret":7,"barre":{"fromString":4,"toString":5,"fret":8}},{"positions":[8,10,10,8,10,8],"baseFret":8,"barre":{"fromString":2,"toString":3,"fret":10}}]}
{"name":"Fm7","variations":[{"positions":[-1,-1,1,3,1,3],"baseFret":1},{"positions":[-1,3,5,3,4,3],"baseFret":1},{"positions":[8,-1,8,8,8,-1],"baseFret":8,"barre":{"fromString":3,"toString":5,"fret":8}}]}
{"name":"Fm9","variations":[{"positions":[-1,3,1,3,3,-1],"baseFret":1,"barre":{"fromString":4,"toString":5,"fret":3}},{"positions":[-1,6,8,7,8,8],"baseFret":6,"barre":{"fromString":5,"toString":6,"fret":8}}]}
{"name":"Fm11","variations":[{"positions":[-1,3,3,3,4,3],"baseFret":1,"barre":{"fromString":2,"toString":4,"fret":3}},{"positions":[8,-1,8,8,6,-1],"baseFret":6,"barre":{"fromString":3,"toString":4,"fret":8}}]}
{"name":"Fm13","variations":[{"positions":[-1,3,-1,3,4,5],"baseFret":1},{"positions":[8,10,8,8,10,8],"baseFret":8,"barre":{"fromString":3,"toString":4,"fret":8}}]}
{"name":"Fm(maj7)","variations":[{"positions":[-1,3,5,4,4,3],"baseFret":1,"barre":{"fromString":4,"toString":5,"fret":4}},{"positions":[8,-1,9,8,8,-1],"baseFret":8,"barre":{"fromString":4,"toString":5,"fret":8}}]}
{"name":"Fsus2","variations":[{"positions":[-1,3,0,0,1,3],"baseFret":1},{"positions":[-1,3,5,7,-1,-1],"baseFret":1},{"positions":[-1,5,5,5,8,8],"baseFret":5,"barre":{"fromString":2,"toString":4,"fret":5}},{"positions":[-1,-1,10,7,8,10],"baseFret":7}]}
{"name":"Fsus4","variations":[{"positions":[-1,3,3,0,1,-1],"baseFret":1,"barre":{"fromString":2,"toString":3,"fret":3}},{"positions":[-1,3,5,5,6,3],"baseFret":1,"barre":{"fromString":3,"toString":4,"fret":5}},{"positions":[8,10,10,10,8,8],"baseFret":8,"barre":{"fromString":2,"toString":4,"fret":10}}]}
{"name":"Fdim","variations":[{"positions":[-1,-1,1,2,1,2],"baseFret":1},{"positions":[-1,3,-1,2,4,2],"baseFret":1}]}
{"name":"Faug","variations":[{"positions":[-1,3,2,1,1,-1],"baseFret":1,"barre":{"fromString":4,"toString":5,"fret":1}},{"positions":[-1,3,-1,5,5,4],"baseFret":1,"barre":{"fromString":4,"toString":5,"fret":5}},{"positions":[-1,-1,6,5,5,8],"baseFret":5,"barre":{"fromString":4,"toString":5,"fret":5}},{"positions":[-1,-1,10,9,9,8],"baseFret":8,"barre":{"fromString":4,"toString":5,"fret":9}}]}
{"name":"F6/9","variations":[{"positions":[-1,3,2,2,3,3],"baseFret":1,"barre":{"fromString":3,"toString":4,"fret":2}},{"positions":[8,-1,5,7,5,5],"baseFret":5,"barre":{"fromString":5,"toString":6,"fret":5}},{"positions":[-1,7,7,7,8,8],"baseFret":7,"barre":{"fromString":2,"toString":4,"fret":7}},{"positions":[-1,10,10,9,10,10],"baseFret":9,"barre":{"fromString":2,"toString":3,"fret":10}}]}
{"name":"F7sus4","variations":[{"positions":[3,-1,3,3,1,-1],"baseFret":1,"barre":{"fromString":3,"toString":4,"fret":3}},{"positions":[-1,3,5,3,6,3],"baseFret":1}]}
{"name":"F7b5","variations":[{"positions":[-1,3,4,3,5,-1],"baseFret":1},{"positions":[8,-1,8,9,7,-1],"baseFret":7}]}
{"name":"F7b9","variations":[{"positions":[-1,3,2,3,2,0],"baseFret":1},{"positions":[-1,5,4,5,4,5],"baseFret":4},{"positions":[8,7,-1,6,8,6],"baseFret":6},{"positions":[8,10,11,9,8,8],"baseFret":8,"barre":{"fromString":5,"toString":6,"fret":8}},{"positions":[8,10,8,9,8,9],"baseFret":8},{"positions":[-1,-1,10,9,11,9],"baseFret":9}]}
{"name":"F9sus4","variations":[{"positions":[-1,3,-1,3,3,1],"baseFret":1,"barre":{"fromString":4,"toString":5,"fret":3}},{"positions":[-1,3,3,3,3,3],"baseFret":1,"barre":{"fromString":2,"toString":6,"fret":3}},{"positions":[8,-1,8,7,6,-1],"baseFret":6},{"positions":[-1,10,10,10,11,10],"baseFret":10,"barre":{"fromString":2,"toString":4,"fret":10}}]}
{"name":"Fadd9","variations":[{"positions":[-1,3,2,0,3,3],"baseFret":1,"barre":{"fromString":5,"toString":6,"fret":3}},{"positions":[-1,3,5,7,5,3],"baseFret":1},{"positions":[-1,5,5,5,5,-1],"baseFret":5,"barre":{"fromString":2,"toString":5,"fret":5}},{"positions":[-1,7,-1,7,8,8],"baseFret":7,"barre":{"fromString":5,"toString":6,"fret":8}}]}
{"name":"Faug9","variations":[{"positions":[0,1,0,1,1,0],"baseFret":1,"barre":{"fromString":4,"toString":5,"fret":1}},{"positions":[8,7,8,7,9,-1],"baseFret":7}]}
{"name":"F#","variations":[{"positions":[-1,4,3,1,2,1],"baseFret":1},{"positions":[-1,4,6,6,6,4],"baseFret":4,"barre":{"fromString":3,"toString":5,"fret":6}},{"positions":[9,8,6,6,6,-1],"baseFret":6,"barre":{"fromString":3,"toString":5,"fret":6}},{"positions":[-1,-1,6,6,6,9],"baseFret":6,"barre":{"fromString":3,"toString":5,"fret":6}},{"positions":[9,11,11,10,9,9],"baseFret":9,"barre":{"fromString":2,"toString":3,"fret":11}}]}
{"name":"F#5","variations":[{"positions":[-1,-1,-1,1,2,4],"baseFret":1},{"positions":[-1,4,6,6,-1,-1],"baseFret":4,"barre":{"fromString":3,"toString":4,"fret":6}},{"positions":[-1,-1,6,6,9,9],"baseFret":6,"barre":{"fromString":3,"toString":4,"fret":6}},{"positions":[9,11,11,-1,-1,-1],"baseFret":9,"barre":{"fromString":2,"toString":3,"fret":11}}]}
{"name":"F#6","variations":[{"positions":[-1,-1,3,3,2,4],"baseFret":1,"barre":{"fromString":3,"toString":4,"fret":3}},{"positions":[-1,4,6,6,6,6],"baseFret":4,"barre":{"fromString":3,"toString":6,"fret":6}},{"positions":[9,-1,8,10,9,-1],"baseFret":8}]}
{"name":"F#7","variations":[{"positions":[-1,4,3,4,2,-1],"baseFret":1},{"positions":[-1,4,6,4,6,4],"baseFret":4},{"positions":[-1,4,6,6,6,7],"baseFret":4,"barre":{"fromString":3,"toString":5,"fret":6}},{"positions":[9,11,9,10,9,9],"baseFret":9,"barre":{"fromString":5,"toString":6,"fret":9}}]}
{"name":"F#maj7","variations":[{"positions":[-1,4,3,1,1,1],"baseFret":1,"barre":{"fromString":4,"toString":6,"fret":1}},{"positions":[-1,4,6,5,6,4],"baseFret":4},{"positions":[-1,-1,11,10,9,8],"baseFret":8},{"positions":[9,-1,10,10,9,-1],"baseFret":9,"barre":{"fromString":3,"toString":4,"fret":10}}]}
{"name":"F#9","variations":[{"positions":[-1,4,3,4,4,4],"baseFret":1,"barre":{"fromString":4,"toString":6,"fret":4}},{"positions":[9,-1,9,8,6,-1],"baseFret":6},{"positions":[9,8,9,8,-1,-1],"baseFret":8},{"positions":[9,11,9,10,9,11],"baseFret":9}]}
{"name":"F#maj9","variations":[{"positions":[-1,4,1,1,1,1],"baseFret":1,"barre":{"fromString":3,"toString":6,"fret":1}},{"positions":[9,-1,10,10,-1,11],"baseFret":9,"barre":{"fromString":3,"toString":4,"fret":10}}]}
{"name":"F#11","variations":[{"positions":[-1,4,3,4,2,2],"baseFret":1,"barre":{"fromString":5,"toString":6,"fret":2}},{"positions":[-1,4,4,4,6,4],"baseFret":4,"barre":{"fromString":2,"toString":4,"fret":4}},{"positions":[9,-1,9,10,7,-1],"baseFret":7},{"positions":[-1,9,9,10,9,9],"baseFret":9,"barre":{"fromString":2,"toString":3,"fret":9}}]}
{"name":"F#13","variations":[{"positions":[-1,4,3,4,4,6],"baseFret":1,"barre":{"fromString":4,"toString":5,"fret":4}},{"positions":[9,-1,9,8,6,6],"baseFret":6,"barre":{"fromString":5,"toString":6,"fret":6}},{"positions":[-1,-1,9,10,11,9],"baseFret":9},{"positions":[9,-1,9,10,11,-1],"baseFret":9}]}
{"name":"F#maj13","variations":[{"positions":[-1,4,-1,5,6,6],"baseFret":4,"barre":{"fromString":5,"toString":6,"fret":6}},{"positions":[9,8,8,8,9,8],"baseFret":8,"barre":{"fromString":2,"toString":4,"fret":8}}]}
{"name":"F#m","variations":[{"positions":[-1,4,6,6,5,4],"baseFret":4,"barre":{"fromString":3,"toString":4,"fret":6}},{"positions":[-1,-1,2,1,2,0],"baseFret":1},{"positions":[-1,7,6,6,9,-1],"baseFret":6,"barre":{"fromString":3,"toString":4,"fret":6}},{"positions":[9,11,11,9,9,9],"baseFret":9,"barre":{"fromString":2,"toString":3,"fret":11}}]}
{"name":"F#m6","variations":[{"positions":[-1,4,-1,3,5,4],"baseFret":1},{"positions":[-1,4,2,3,2,4],"baseFret":1},{"positions":[9,-1,8,9,9,-1],"baseFret":8,"barre":{"fromString":4,"toString":5,"fret":9}},{"positions":[9,11,11,9,11,9],"baseFret":9,"barre":{"fromString":2,"toString":3,"fret":11}}]}
{"name":"F#m7","variations":[{"positions":[-1,4,2,1,0,0],"baseFret":1},{"positions":[-1,4,-1,4,5,4],"baseFret":4},{"positions":[9,-1,9,9,9,-1],"baseFret":9,"barre":{"fromString":3,"toString":5,"fret":9}}]}
{"name":"F#m9","variations":[{"positions":[-1,4,2,4,4,-1],"baseFret":1,"barre":{"fromString":4,"toString":5,"fret":4}},{"positions":[9,-1,9,9,9,11],"baseFret":9,"barre":{"fromString":3,"toString":5,"fret":9}}]}
{"name":"F#m11","variations":[{"positions":[-1,4,1,4,4,1],"baseFret":1,"barre":{"fromString":4,"toString":5,"fret":4}},{"positions":[-1,4,4,4,5,4],"baseFret":4,"barre":{"fromString":2,"toString":4,"fret":4}}]}
{"name":"F#m13","variations":[{"positions":[-1,1,-1,1,2,3],"baseFret":1},{"positions":[9,11,9,9,11,9],"baseFret":9,"barre":{"fromString":3,"toString":4,"fret":9}}]}
{"name":"F#m(maj7)","variations":[{"positions":[-1,4,6,5,5,4],"baseFret":4,"barre":{"fromString":4,"toString":5,"fret":5}},{"positions":[9,11,10,9,9,9],"baseFret":9,"barre":{"fromString":4,"toString":6,"fret":9}}]}
{"name":"F#sus2","variations":[{"positions":[-1,-1,1,1,2,-1],"baseFret":1,"barre":{"fromString":3,"toString":4,"fret":1}},{"positions":[-1,4,6,6,4,4],"baseFret":4,"barre":{"fromString":3,"toString":4,"fret":6}},{"positions":[-1,6,6,6,9,9],"baseFret":6,"barre":{"fromString":2,"toString":4,"fret":6}},{"positions":[9,-1,-1,8,10,-1],"baseFret":8}]}
{"name":"F#sus4","variations":[{"positions":[-1,4,6,6,7,-1],"baseFret":4,"barre":{"fromString":3,"toString":4,"fret":6}},{"positions":[-1,-1,6,6,4,7],"baseFret":4,"barre":{"fromString":3,"toString":4,"fret":6}},{"positions":[-1,4,6,6,7,4],"baseFret":4,"barre":{"fromString":3,"toString":4,"fret":6}},{"positions":[9,11,11,11,9,9],"baseFret":9,"barre":{"fromString":2,"toString":4,"fret":11}}]}
{"name":"F#dim","variations":[{"positions":[-1,-1,2,3,2,3],"baseFret":1},{"positions":[9,-1,8,9,8,-1],"baseFret":8}]}
{"name":"F#aug","variations":[{"positions":[-1,4,3,2,2,-1],"baseFret":1,"barre":{"fromString":4,"toString":5,"fret":2}},{"positions":[-1,4,-1,6,6,5],"baseFret":4,"barre":{"fromString":4,"toString":5,"fret":6}},{"positions":[-1,-1,7,6,6,9],"baseFret":6,"barre":{"fromString":4,"toString":5,"fret":6}},{"positions":[-1,-1,11,10,10,9],"baseFret":9,"barre":{"fromString":4,"toString":5,"fret":10}}]}
{"name":"F#6/9","variations":[{"positions":[-1,1,1,1,2,1],"baseFret":1,"barre":{"fromString":2,"toString":4,"fret":1}},{"positions":[9,-1,6,8,6,6],"baseFret":6,"barre":{"fromString":5,"toString":6,"fret":6}},{"positions":[9,8,8,8,9,9],"baseFret":8,"barre":{"fromString":2,"toString":4,"fret":8}},{"positions":[-1,11,11,10,11,11],"baseFret":10,"barre":{"fromString":2,"toString":3,"fret":11}}]}
{"name":"F#7sus4","variations":[{"positions":[4,-1,4,4,2,-1],"baseFret":1,"barre":{"fromString":3,"toString":4,"fret":4}},{"positions":[-1,4,6,4,7,4],"baseFret":4}]}
{"name":"F#7b5","variations":[{"positions":[3,-1,3,4,2,-1],"baseFret":1},{"positions":[9,-1,9,10,8,-1],"baseFret":8}]}
{"name":"F#7b9","variations":[{"positions":[-1,4,-1,4,3,1],"baseFret":1},{"positions":[-1,4,3,4,3,4],"baseFret":1},{"positions":[-1,4,3,4,3,-1],"baseFret":1},{"positions":[9,8,-1,7,9,7],"baseFret":7},{"positions":[9,11,12,10,9,9],"baseFret":9,"barre":{"fromString":5,"toString":6,"fret":9}},{"positions":[9,11,9,10,9,10],"baseFret":9}]}
{"name":"F#9sus4","variations":[{"positions":[-1,4,-1,4,4,2],"baseFret":1,"barre":{"fromString":4,"toString":5,"fret":4}},{"positions":[-1,4,4,4,4,4],"baseFret":4,"barre":{"fromString":2,"toString":6,"fret":4}},{"positions":[9,-1,9,8,7,-1],"baseFret":7},{"positions":[-1,11,11,11,12,11],"baseFret":11,"barre":{"fromString":2,"toString":4,"fret":11}}]}
{"name":"F#add9","variations":[{"positions":[-1,4,3,1,4,-1],"baseFret":1},{"positions":[-1,4,6,8,6,-1],"baseFret":4},{"positions":[-1,6,6,6,6,-1],"baseFret":6,"barre":{"fromString":2,"toString":5,"fret":6}},{"positions":[-1,8,-1,8,9,9],"baseFret":8,"barre":{"fromString":5,"toString":6,"fret":9}}]}
{"name":"F#aug9","variations":[{"positions":[-1,4,3,4,4,5],"baseFret":1,"barre":{"fromString":4,"toString":5,"fret":4}},{"positions":[9,8,9,8,10,-1],"baseFret":8}]}
{"name":"G","variations":[{"positions":[-1,-1,0,2,3,2],"baseFret":1},{"positions":[-1,-1,4,2,4,5],"baseFret":1},{"positions":[-1,5,4,2,3,2],"baseFret":1},{"positions":[-1,5,7,7,7,5],"baseFret":5,"barre":{"fromString":3,"toString":5,"fret":7}},{"positions":[10,9,7,7,7,-1],"baseFret":7,"barre":{"fromString":3,"toString":5,"fret":7}},{"positions":[-1,-1,7,7,7,10],"baseFret":7,"barre":{"fromString":3,"toString":5,"fret":7}}]}
{"name":"G5","variations":[{"positions":[-1,-1,0,2,3,-1],"baseFret":1},{"positions":[-1,5,7,7,-1,-1],"baseFret":5,"barre":{"fromString":3,"toString":4,"fret":7}},{"positions":[-1,-1,7,7,10,10],"baseFret":7,"barre":{"fromString":3,"toString":4,"fret":7}}]}
{"name":"G6","variations":[{"positions":[-1,-1,0,2,0,2],"baseFret":1},{"positions":[-1,5,7,7,7,7],"baseFret":5,"barre":{"fromString":3,"toString":6,"fret":7}},{"positions":[10,-1,9,11,10,-1],"baseFret":9}]}
{"name":"G7","variations":[{"positions":[-1,-1,0,2,1,2],"baseFret":1},{"positions":[-1,5,4,5,3,-1],"baseFret":1},{"positions":[-1,-1,4,5,3,5],"baseFret":1},{"positions":[-1,5,7,7,7,8],"baseFret":5,"barre":{"fromString":3,"toString":5,"fret":7}},{"positions":[-1,5,7,5,7,5],"baseFret":5}]}
{"name":"Gmaj7","variations":[{"positions":[-1,5,4,2,2,2],"baseFret":1,"barre":{"fromString":4,"toString":6,"fret":2}},{"positions":[-1,5,7,6,7,5],"baseFret":5},{"positions":[-1,-1,7,7,7,9],"baseFret":7,"barre":{"fromString":3,"toString":5,"fret":7}}]}
{"name":"G9","variations":[{"positions":[-1,5,4,2,1,0],"baseFret":1},{"positions":[-1,5,4,5,5,5],"baseFret":4,"barre":{"fromString":4,"toString":6,"fret":5}},{"positions":[10,-1,10,9,7,-1],"baseFret":7}]}
{"name":"Gmaj9","variations":[{"positions":[-1,5,2,2,2,2],"baseFret":1,"barre":{"fromString":3,"toString":6,"fret":2}},{"positions":[10,-1,11,11,-1,12],"baseFret":10,"barre":{"fromString":3,"toString":4,"fret":11}}]}
{"name":"G11","variations":[{"positions":[-1,-1,0,0,1,2],"baseFret":1},{"positions":[-1,5,4,5,3,3],"baseFret":1,"barre":{"fromString":5,"toString":6,"fret":3}},{"positions":[-1,5,5,5,7,5],"baseFret":5,"barre":{"fromString":2,"toString":4,"fret":5}},{"positions":[-1,9,-1,7,8,8],"baseFret":7,"barre":{"fromString":5,"toString":6,"fret":8}}]}
{"name":"G13","variations":[{"positions":[-1,3,4,4,3,-1],"baseFret":1,"barre":{"fromString":3,"toString":4,"fret":4}},{"positions":[-1,5,-1,5,7,7],"baseFret":5,"barre":{"fromString":5,"toString":6,"fret":7}},{"positions":[-1,-1,10,7,7,7],"baseFret":7,"barre":{"fromString":4,"toString":6,"fret":7}}]}
{"name":"Gmaj13","variations":[{"positions":[-1,5,-1,6,7,7],"baseFret":5,"barre":{"fromString":5,"toString":6,"fret":7}},{"positions":[10,9,9,9,10,9],"baseFret":9,"barre":{"fromString":2,"toString":4,"fret":9}}]}
{"name":"Gm","variations":[{"positions":[-1,-1,0,2,3,1],"baseFret":1},{"positions":[-1,5,3,2,3,-1],"baseFret":1},{"positions":[-1,5,7,7,6,5],"baseFret":5,"barre":{"fromString":3,"toString":4,"fret":7}},{"positions":[-1,8,7,7,6,-1],"baseFret":6,"barre":{"fromString":3,"toString":4,"fret":7}},{"positions":[-1,8,7,7,10,-1],"baseFret":7,"barre":{"fromString":3,"toString":4,"fret":7}},{"positions":[-1,-1,7,10,10,10],"baseFret":7,"barre":{"fromString":4,"toString":6,"fret":10}}]}
{"name":"Gm6","variations":[{"positions":[-1,-1,0,2,0,1],"baseFret":1},{"positions":[-1,5,3,4,3,5],"baseFret":1},{"positions":[-1,5,7,-1,6,8],"baseFret":5},{"positions":[10,-1,9,10,10,-1],"baseFret":9,"barre":{"fromString":4,"toString":5,"fret":10}}]}
{"name":"Gm7","variations":[{"positions":[-1,-1,0,2,1,1],"baseFret":1,"barre":{"fromString":5,"toString":6,"fret":1}},{"positions":[-1,5,7,5,6,5],"baseFret":5},{"positions":[-1,-1,7,7,6,8],"baseFret":6,"barre":{"fromString":3,"toString":4,"fret":7}},{"positions":[10,-1,10,10,10,-1],"baseFret":10,"barre":{"fromString":3,"toString":5,"fret":10}}]}
{"name":"Gm9","variations":[{"positions":[-1,5,3,5,5,-1],"baseFret":1,"barre":{"fromString":4,"toString":5,"fret":5}},{"positions":[10,-1,10,10,10,12],"baseFret":10,"barre":{"fromString":3,"toString":5,"fret":10}}]}
{"name":"Gm11","variations":[{"positions":[-1,-1,0,0,1,1],"baseFret":1,"barre":{"fromString":5,"toString":6,"fret":1}},{"positions":[-1,5,5,5,6,5],"baseFret":5,"barre":{"fromString":2,"toString":4,"fret":5}}]}
{"name":"Gm13","variations":[{"positions":[-1,-1,0,4,1,1],"baseFret":1,"barre":{"fromString":5,"toString":6,"fret":1}},{"positions":[10,12,10,10,12,10],"baseFret":10,"barre":{"fromString":3,"toString":4,"fret":10}}]}
{"name":"Gm(maj7)","variations":[{"positions":[-1,-1,0,2,2,1],"baseFret":1,"barre":{"fromString":4,"toString":5,"fret":2}},{"positions":[-1,5,7,6,6,5],"baseFret":5,"barre":{"fromString":4,"toString":5,"fret":6}}]}
{"name":"Gsus2","variations":[{"positions":[-1,-1,0,2,3,0],"baseFret":1},{"positions":[-1,5,7,7,5,5],"baseFret":5,"barre":{"fromString":3,"toString":4,"fret":7}},{"positions":[-1,7,7,9,10,10],"baseFret":7,"barre":{"fromString":2,"toString":3,"fret":7}}]}
{"name":"Gsus4","variations":[{"positions":[-1,-1,0,2,3,3],"baseFret":1,"barre":{"fromString":5,"toString":6,"fret":3}},{"positions":[-1,5,7,7,8,5],"baseFret":5,"barre":{"fromString":3,"toString":4,"fret":7}},{"positions":[-1,-1,7,7,8,10],"baseFret":7,"barre":{"fromString":3,"toString":4,"fret":7}}]}
{"name":"Gdim","variations":[{"positions":[-1,-1,0,1,0,1],"baseFret":1},{"positions":[-1,5,-1,4,6,4],"baseFret":4}]}
{"name":"Gaug","variations":[{"positions":[-1,-1,0,3,3,2],"baseFret":1,"barre":{"fromString":4,"toString":5,"fret":3}},{"positions":[-1,5,4,3,3,-1],"baseFret":1,"barre":{"fromString":4,"toString":5,"fret":3}},{"positions":[-1,5,-1,7,7,6],"baseFret":5,"barre":{"fromString":4,"toString":5,"fret":7}},{"positions":[-1,-1,8,7,7,10],"baseFret":7,"barre":{"fromString":4,"toString":5,"fret":7}}]}
{"name":"G6/9","variations":[{"positions":[-1,5,4,2,0,0],"baseFret":1},{"positions":[-1,5,4,4,5,5],"baseFret":4,"barre":{"fromString":3,"toString":4,"fret":4}},{"positions":[10,-1,7,9,7,7],"baseFret":7,"barre":{"fromString":5,"toString":6,"fret":7}},{"positions":[-1,9,9,9,10,10],"baseFret":9,"barre":{"fromString":2,"toString":4,"fret":9}}]}
{"name":"G7sus4","variations":[{"positions":[-1,-1,0,2,1,3],"baseFret":1},{"positions":[10,12,10,12,13,10],"baseFret":10}]}
{"name":"G7b5","variations":[{"positions":[-1,-1,0,1,1,2],"baseFret":1,"barre":{"fromString":4,"toString":5,"fret":1}},{"positions":[-1,5,6,5,7,-1],"baseFret":5}]}
{"name":"G7b9","variations":[{"positions":[-1,-1,0,5,4,2],"baseFret":1},{"positions":[-1,5,4,5,4,5],"baseFret":4},{"positions":[-1,5,4,5,4,-1],"baseFret":4},{"positions":[10,9,-1,8,10,8],"baseFret":8}]}
{"name":"G9sus4","variations":[{"positions":[-1,5,-1,5,5,3],"baseFret":1,"barre":{"fromString":4,"toString":5,"fret":5}},{"positions":[-1,5,5,5,5,5],"baseFret":5,"barre":{"fromString":2,"toString":6,"fret":5}},{"positions":[10,-1,10,9,8,-1],"baseFret":8}]}
{"name":"Gadd9","variations":[{"positions":[-1,-1,4,2,3,0],"baseFret":1},{"positions":[5,-1,4,7,5,-1],"baseFret":4},{"positions":[-1,7,7,7,7,-1],"baseFret":7,"barre":{"fromString":2,"toString":5,"fret":7}},{"positions":[-1,9,-1,9,10,10],"baseFret":9,"barre":{"fromString":5,"toString":6,"fret":10}}]}
{"name":"Gaug9","variations":[{"positions":[2,3,2,3,3,2],"baseFret":1,"barre":{"fromString":4,"toString":5,"fret":3}},{"positions":[10,9,10,9,11,-1],"baseFret":9}]}
{"name":"Ab","variations":[{"positions":[-1,-1,1,3,4,3],"baseFret":1},{"positions":[-1,6,5,3,4,3],"baseFret":1},{"positions":[-1,-1,5,3,4,6],"baseFret":1},{"positions":[-1,6,8,8,8,6],"baseFret":6,"barre":{"fromString":3,"toString":5,"fret":8}},{"positions":[-1,-1,8,8,8,11],"baseFret":8,"barre":{"fromString":3,"toString":5,"fret":8}}]}
{"name":"Ab","variations":[{"positions":[-1,-1,1,3,4,-1],"baseFret":1},{"positions":[-1,6,8,8,-1,-1],"baseFret":6,"barre":{"fromString":3,"toString":4,"fret":8}},{"positions":[-1,-1,8,8,11,11],"baseFret":8,"barre":{"fromString":3,"toString":4,"fret":8}}]}
{"name":"Ab6","variations":[{"positions":[-1,-1,1,3,1,3],"baseFret":1},{"positions":[-1,6,8,8,8,8],"baseFret":6,"barre":{"fromString":3,"toString":6,"fret":8}},{"positions":[-1,10,10,8,11,-1],"baseFret":8,"barre":{"fromString":2,"toString":3,"fret":10}},{"positions":[11,-1,10,12,11,-1],"baseFret":10}]}
{"name":"Ab7","variations":[{"positions":[-1,-1,1,3,2,3],"baseFret":1},{"positions":[-1,4,-1,3,4,3],"baseFret":1},{"positions":[-1,6,8,6,8,6],"baseFret":6},{"positions":[-1,6,8,8,8,9],"baseFret":6,"barre":{"fromString":3,"toString":5,"fret":8}},{"positions":[-1,10,11,8,11,-1],"baseFret":8}]}
{"name":"Abmaj7","variations":[{"positions":[-1,-1,1,3,3,3],"baseFret":1,"barre":{"fromString":4,"toString":6,"fret":3}},{"positions":[-1,6,5,3,3,3],"baseFret":1,"barre":{"fromString":4,"toString":6,"fret":3}},{"positions":[-1,6,8,7,8,6],"baseFret":6}]}
{"name":"Ab9","variations":[{"positions":[-1,-1,1,0,2,1],"baseFret":1},{"positions":[-1,6,5,6,6,6],"baseFret":5,"barre":{"fromString":4,"toString":6,"fret":6}},{"positions":[-1,-1,10,9,8,10],"baseFret":8}]}
{"name":"Abmaj9","variations":[{"positions":[-1,-1,1,0,3,1],"baseFret":1},{"positions":[-1,6,3,3,3,3],"baseFret":1,"barre":{"fromString":3,"toString":6,"fret":3}}]}
{"name":"Ab11","variations":[{"positions":[-1,-1,1,1,2,3],"baseFret":1,"barre":{"fromString":3,"toString":4,"fret":1}},{"positions":[4,4,5,6,4,4],"baseFret":4,"barre":{"fromString":1,"toString":2,"fret":4}},{"positions":[-1,6,5,6,4,4],"baseFret":4,"barre":{"fromString":5,"toString":6,"fret":4}},{"positions":[-1,6,6,6,8,6],"baseFret":6,"barre":{"fromString":2,"toString":4,"fret":6}}]}
{"name":"Ab13","variations":[{"positions":[-1,4,5,5,4,-1],"baseFret":4,"barre":{"fromString":3,"toString":4,"fret":5}},{"positions":[-1,6,5,6,6,8],"baseFret":5,"barre":{"fromString":4,"toString":5,"fret":6}},{"positions":[-1,-1,11,8,8,8],"baseFret":8,"barre":{"fromString":4,"toString":6,"fret":8}}]}
{"name":"Abmaj13","variations":[{"positions":[-1,2,1,3,4,4],"baseFret":1,"barre":{"fromString":5,"toString":6,"fret":4}},{"positions":[11,10,10,10,11,10],"baseFret":10,"barre":{"fromString":2,"toString":4,"fret":10}}]}
{"name":"Abm","variations":[{"positions":[2,-1,1,3,4,-1],"baseFret":1},{"positions":[-1,1,4,3,4,-1],"baseFret":1},{"positions":[-1,6,4,3,4,-1],"baseFret":1},{"positions":[-1,6,8,8,7,6],"baseFret":6,"barre":{"fromString":3,"toString":4,"fret":8}},{"positions":[-1,9,8,8,7,-1],"baseFret":7,"barre":{"fromString":3,"toString":4,"fret":8}},{"positions":[-1,-1,8,11,11,11],"baseFret":8,"barre":{"fromString":4,"toString":6,"fret":11}}]}
{"name":"Abm6","variations":[{"positions":[-1,-1,1,3,1,2],"baseFret":1},{"positions":[-1,3,4,3,4,-1],"baseFret":1},{"positions":[-1,6,-1,5,7,6],"baseFret":5},{"positions":[11,-1,10,11,11,-1],"baseFret":10,"barre":{"fromString":4,"toString":5,"fret":11}}]}
{"name":"Abm7","variations":[{"positions":[-1,-1,1,3,2,2],"baseFret":1,"barre":{"fromString":5,"toString":6,"fret":2}},{"positions":[-1,4,4,3,4,-1],"baseFret":1,"barre":{"fromString":2,"toString":3,"fret":4}},{"positions":[-1,6,8,6,7,6],"baseFret":6},{"positions":[11,-1,11,11,11,-1],"baseFret":11,"barre":{"fromString":3,"toString":5,"fret":11}}]}
{"name":"Abm9","variations":[{"positions":[2,-1,1,3,2,1],"baseFret":1},{"positions":[11,-1,11,11,11,13],"baseFret":11,"barre":{"fromString":3,"toString":5,"fret":11}}]}
{"name":"Abm11","variations":[{"positions":[-1,1,1,1,2,2],"baseFret":1,"barre":{"fromString":2,"toString":4,"fret":1}},{"positions":[11,11,11,11,11,11],"baseFret":11,"barre":{"fromString":1,"toString":6,"fret":11}}]}
{"name":"Abm13","variations":[{"positions":[-1,6,-1,6,7,8],"baseFret":6},{"positions":[11,13,11,11,13,11],"baseFret":11,"barre":{"fromString":3,"toString":4,"fret":11}}]}
{"name":"Abm(maj7)","variations":[{"positions":[-1,-1,1,3,3,2],"baseFret":1,"barre":{"fromString":4,"toString":5,"fret":3}},{"positions":[-1,6,8,7,7,6],"baseFret":6,"barre":{"fromString":4,"toString":5,"fret":7}}]}
{"name":"Absus2","variations":[{"positions":[-1,-1,1,3,4,1],"baseFret":1},{"positions":[-1,6,8,8,6,6],"baseFret":6,"barre":{"fromString":3,"toString":4,"fret":8}},{"positions":[-1,8,8,10,11,11],"baseFret":8,"barre":{"fromString":2,"toString":3,"fret":8}},{"positions":[11,-1,8,10,11,-1],"baseFret":8}]}
{"name":"Absus4","variations":[{"positions":[-1,-1,1,3,4,4],"baseFret":1,"barre":{"fromString":5,"toString":6,"fret":4}},{"positions":[-1,-1,8,8,9,6],"baseFret":6,"barre":{"fromString":3,"toString":4,"fret":8}},{"positions":[-1,6,8,8,9,6],"baseFret":6,"barre":{"fromString":3,"toString":4,"fret":8}}]}
{"name":"Abdim","variations":[{"positions":[-1,-1,1,2,1,2],"baseFret":1},{"positions":[-1,6,7,5,7,-1],"baseFret":5}]}
{"name":"Abaug","variations":[{"positions":[-1,-1,1,0,0,3],"baseFret":1},{"positions":[-1,-1,5,4,4,3],"baseFret":1,"barre":{"fromString":4,"toString":5,"fret":4}},{"positions":[-1,6,5,4,4,-1],"baseFret":4,"barre":{"fromString":4,"toString":5,"fret":4}},{"positions":[-1,6,-1,8,8,7],"baseFret":6,"barre":{"fromString":4,"toString":5,"fret":8}}]}
{"name":"Ab6/9","variations":[{"positions":[-1,3,3,3,4,3],"baseFret":1,"barre":{"fromString":2,"toString":4,"fret":3}},{"positions":[-1,6,5,5,6,6],"baseFret":5,"barre":{"fromString":3,"toString":4,"fret":5}},{"positions":[11,8,8,8,8,8],"baseFret":8,"barre":{"fromString":2,"toString":6,"fret":8}},{"positions":[11,-1,8,10,8,8],"baseFret":8,"barre":{"fromString":5,"toString":6,"fret":8}}]}
{"name":"Ab7sus4","variations":[{"positions":[-1,-1,1,1,2,-1],"baseFret":1,"barre":{"fromString":3,"toString":4,"fret":1}},{"positions":[-1,6,8,6,9,-1],"baseFret":6}]}
{"name":"Ab7b5","variations":[{"positions":[-1,-1,1,2,2,3],"baseFret":1,"barre":{"fromString":4,"toString":5,"fret":2}},{"positions":[-1,6,7,6,8,-1],"baseFret":6}]}
{"name":"Ab7b9","variations":[{"positions":[-1,6,-1,6,5,3],"baseFret":1},{"positions":[-1,6,5,6,5,6],"baseFret":5},{"positions":[-1,6,5,6,5,-1],"baseFret":5},{"positions":[11,10,-1,9,11,9],"baseFret":9}]}
{"name":"Ab9sus4","variations":[{"positions":[-1,-1,1,1,2,1],"baseFret":1,"barre":{"fromString":3,"toString":4,"fret":1}},{"positions":[-1,6,-1,6,6,4],"baseFret":4,"barre":{"fromString":4,"toString":5,"fret":6}},{"positions":[-1,6,6,6,6,6],"baseFret":6,"barre":{"fromString":2,"toString":6,"fret":6}},{"positions":[11,-1,11,10,9,-1],"baseFret":9}]}
{"name":"Abadd9","variations":[{"positions":[-1,-1,3,3,4,3],"baseFret":1,"barre":{"fromString":3,"toString":4,"fret":3}},{"positions":[-1,6,5,3,6,-1],"baseFret":1},{"positions":[-1,8,8,8,8,-1],"baseFret":8,"barre":{"fromString":2,"toString":5,"fret":8}},{"positions":[-1,10,-1,10,11,11],"baseFret":10,"barre":{"fromString":5,"toString":6,"fret":11}}]}
{"name":"Abaug9","variations":[{"positions":[3,4,3,4,4,3],"baseFret":1,"barre":{"fromString":4,"toString":5,"fret":4}},{"positions":[11,10,11,10,12,-1],"baseFret":10}]}
{"name":"A","variations":[{"positions":[0,2,2,1,0,0],"baseFret":1,"barre":{"fromString":2,"toString":3,"fret":2}},{"positions":[0,2,2,4,5,4],"baseFret":1,"barre":{"fromString":2,"toString":3,"fret":2}},{"positions":[-1,7,6,4,5,4],"baseFret":4},{"positions":[-1,-1,6,4,5,7],"baseFret":4},{"positions":[-1,7,9,9,9,7],"baseFret":7,"barre":{"fromString":3,"toString":5,"fret":9}}]}
{"name":"A5","variations":[{"positions":[0,2,2,-1,-1,-1],"baseFret":1,"barre":{"fromString":2,"toString":3,"fret":2}},{"positions":[-1,-1,2,4,5,-1],"baseFret":1},{"positions":[-1,7,9,9,-1,-1],"baseFret":7,"barre":{"fromString":3,"toString":4,"fret":9}}]}
{"name":"A6","variations":[{"positions":[-1,-1,2,4,2,4],"baseFret":1},{"positions":[0,2,2,1,2,0],"baseFret":1,"barre":{"fromString":2,"toString":3,"fret":2}},{"positions":[-1,7,9,9,9,9],"baseFret":7,"barre":{"fromString":3,"toString":6,"fret":9}}]}
{"name":"A7","variations":[{"positions":[0,2,0,1,0,0],"baseFret":1},{"positions":[0,2,2,1,3,0],"baseFret":1,"barre":{"fromString":2,"toString":3,"fret":2}},{"positions":[4,-1,2,4,3,-1],"baseFret":1},{"positions":[-1,7,6,7,5,-1],"baseFret":5},{"positions":[-1,7,9,7,9,7],"baseFret":7},{"positions":[-1,7,9,9,9,10],"baseFret":7,"barre":{"fromString":3,"toString":5,"fret":9}}]}
{"name":"Amaj7","variations":[{"positions":[0,2,1,1,0,0],"baseFret":1,"barre":{"fromString":3,"toString":4,"fret":1}},{"positions":[-1,7,6,4,4,4],"baseFret":4,"barre":{"fromString":4,"toString":6,"fret":4}},{"positions":[-1,-1,9,9,9,11],"baseFret":9,"barre":{"fromString":3,"toString":5,"fret":9}}]}
{"name":"A9","variations":[{"positions":[4,-1,2,4,3,2],"baseFret":1},{"positions":[0,2,0,1,0,2],"baseFret":1},{"positions":[-1,7,6,7,7,7],"baseFret":6,"barre":{"fromString":4,"toString":6,"fret":7}}]}
{"name":"Amaj9","variations":[{"positions":[0,2,4,4,4,4],"baseFret":1,"barre":{"fromString":3,"toString":6,"fret":4}},{"positions":[-1,7,4,4,4,4],"baseFret":4,"barre":{"fromString":3,"toString":6,"fret":4}}]}
{"name":"A11","variations":[{"positions":[0,0,2,1,3,2],"baseFret":1},{"positions":[-1,-1,2,2,3,4],"baseFret":1,"barre":{"fromString":3,"toString":4,"fret":2}},{"positions":[-1,7,6,7,5,5],"baseFret":5,"barre":{"fromString":5,"toString":6,"fret":5}},{"positions":[-1,7,7,7,9,7],"baseFret":7,"barre":{"fromString":2,"toString":4,"fret":7}}]}
{"name":"A13","variations":[{"positions":[0,2,0,1,2,2],"baseFret":1,"barre":{"fromString":5,"toString":6,"fret":2}},{"positions":[-1,5,6,6,5,-1],"baseFret":5,"barre":{"fromString":3,"toString":4,"fret":6}},{"positions":[-1,7,-1,7,9,9],"baseFret":7,"barre":{"fromString":5,"toString":6,"fret":9}}]}
{"name":"Amaj13","variations":[{"positions":[0,2,1,1,2,2],"baseFret":1,"barre":{"fromString":3,"toString":4,"fret":1}},{"positions":[12,11,11,11,12,11],"baseFret":11,"barre":{"fromString":2,"toString":4,"fret":11}}]}
{"name":"Am","variations":[{"positions":[0,2,2,0,0,0],"baseFret":1,"barre":{"fromString":2,"toString":3,"fret":2}},{"positions":[-1,-1,2,4,5,3],"baseFret":1},{"positions":[-1,-1,5,4,5,3],"baseFret":1},{"positions":[-1,7,5,4,5,-1],"baseFret":4},{"positions":[-1,7,9,9,8,7],"baseFret":7,"barre":{"fromString":3,"toString":4,"fret":9}},{"positions":[-1,10,9,9,8,-1],"baseFret":8,"barre":{"fromString":3,"toString":4,"fret":9}}]}
{"name":"Am6","variations":[{"positions":[0,2,2,0,2,0],"baseFret":1,"barre":{"fromString":2,"toString":3,"fret":2}},{"positions":[-1,7,5,6,5,7],"baseFret":5},{"positions":[-1,7,-1,6,8,7],"baseFret":6},{"positions":[12,-1,11,12,12,-1],"baseFret":11,"barre":{"fromString":4,"toString":5,"fret":12}}]}
{"name":"Am7","variations":[{"positions":[0,2,0,0,0,0],"baseFret":1},{"positions":[0,2,2,0,3,0],"baseFret":1,"barre":{"fromString":2,"toString":3,"fret":2}},{"positions":[-1,7,9,7,8,7],"baseFret":7},{"positions":[-1,7,-1,7,8,7],"baseFret":7}]}
{"name":"Am9","variations":[{"positions":[0,2,0,0,0,2],"baseFret":1},{"positions":[-1,7,5,7,7,-1],"baseFret":5,"barre":{"fromString":4,"toString":5,"fret":7}}]}
{"name":"Am11","variations":[{"positions":[0,0,0,0,0,0],"baseFret":1},{"positions":[-1,7,7,7,8,7],"baseFret":7,"barre":{"fromString":2,"toString":4,"fret":7}}]}
{"name":"Am13","variations":[{"positions":[0,2,0,0,2,2],"baseFret":1,"barre":{"fromString":5,"toString":6,"fret":2}},{"positions":[-1,7,-1,7,8,9],"baseFret":7}]}
{"name":"Am(maj7)","variations":[{"positions":[0,2,1,0,0,0],"baseFret":1},{"positions":[-1,7,5,4,4,-1],"baseFret":4,"barre":{"fromString":4,"toString":5,"fret":4}}]}
{"name":"Asus2","variations":[{"positions":[-1,-1,2,4,5,2],"baseFret":1},{"positions":[-1,-1,4,4,5,7],"baseFret":4,"barre":{"fromString":3,"toString":4,"fret":4}},{"positions":[-1,7,9,9,7,7],"baseFret":7,"barre":{"fromString":3,"toString":4,"fret":9}}]}
{"name":"Asus4","variations":[{"positions":[0,2,2,2,0,0],"baseFret":1,"barre":{"fromString":2,"toString":4,"fret":2}},{"positions":[-1,-1,2,4,5,5],"baseFret":1,"barre":{"fromString":5,"toString":6,"fret":5}},{"positions":[-1,7,7,9,10,7],"baseFret":7,"barre":{"fromString":2,"toString":3,"fret":7}},{"positions":[-1,7,9,9,10,-1],"baseFret":7,"barre":{"fromString":3,"toString":4,"fret":9}}]}
{"name":"Adim","variations":[{"positions":[-1,-1,2,3,2,3],"baseFret":1},{"positions":[12,-1,11,12,11,-1],"baseFret":11}]}
{"name":"Aaug","variations":[{"positions":[-1,-1,2,1,1,0],"baseFret":1,"barre":{"fromString":4,"toString":5,"fret":1}},{"positions":[4,-1,-1,5,5,4],"baseFret":4,"barre":{"fromString":4,"toString":5,"fret":5}},{"positions":[-1,7,6,5,5,-1],"baseFret":5,"barre":{"fromString":4,"toString":5,"fret":5}},{"positions":[-1,7,-1,9,9,8],"baseFret":7,"barre":{"fromString":4,"toString":5,"fret":9}}]}
{"name":"A6/9","variations":[{"positions":[0,2,-1,1,2,2],"baseFret":1,"barre":{"fromString":5,"toString":6,"fret":2}},{"positions":[-1,4,4,4,5,4],"baseFret":4,"barre":{"fromString":2,"toString":4,"fret":4}}]}
{"name":"A7sus4","variations":[{"positions":[-1,2,2,2,3,-1],"baseFret":1,"barre":{"fromString":2,"toString":4,"fret":2}},{"positions":[-1,7,9,7,10,-1],"baseFret":7}]}
{"name":"A7b5","variations":[{"positions":[-1,-1,2,3,3,4],"baseFret":1,"barre":{"fromString":4,"toString":5,"fret":3}},{"positions":[-1,7,8,7,9,-1],"baseFret":7}]}
{"name":"A7b9","variations":[{"positions":[0,2,3,1,3,-1],"baseFret":1},{"positions":[-1,7,6,7,6,7],"baseFret":6},{"positions":[-1,7,6,7,6,-1],"baseFret":6}]}
{"name":"A9sus4","variations":[{"positions":[-1,2,2,2,3,2],"baseFret":1,"barre":{"fromString":2,"toString":4,"fret":2}},{"positions":[-1,7,-1,7,7,5],"baseFret":5,"barre":{"fromString":4,"toString":5,"fret":7}},{"positions":[-1,7,7,7,7,7],"baseFret":7,"barre":{"fromString":2,"toString":6,"fret":7}}]}
{"name":"Aadd9","variations":[{"positions":[-1,-1,4,4,5,4],"baseFret":4,"barre":{"fromString":3,"toString":4,"fret":4}},{"positions":[0,2,2,1,0,2],"baseFret":1,"barre":{"fromString":2,"toString":3,"fret":2}},{"positions":[7,-1,6,9,7,-1],"baseFret":6},{"positions":[-1,9,9,9,9,-1],"baseFret":9,"barre":{"fromString":2,"toString":5,"fret":9}}]}
{"name":"Aaug9","variations":[{"positions":[0,3,0,1,1,2],"baseFret":1,"barre":{"fromString":4,"toString":5,"fret":1}},{"positions":[-1,7,6,7,7,8],"baseFret":6,"barre":{"fromString":4,"toString":5,"fret":7}}]}
{"name":"Bb","variations":[{"positions":[1,3,3,2,1,1],"baseFret":1,"barre":{"fromString":2,"toString":3,"fret":3}},{"positions":[5,-1,3,5,6,-1],"baseFret":1},{"positions":[-1,8,7,5,6,5],"baseFret":5},{"positions":[8,-1,7,5,6,-1],"baseFret":5},{"positions":[-1,-1,7,5,6,8],"baseFret":5},{"positions":[-1,8,10,10,10,8],"baseFret":8,"barre":{"fromString":3,"toString":5,"fret":10}}]}
{"name":"Bb5","variations":[{"positions":[1,3,3,-1,-1,-1],"baseFret":1,"barre":{"fromString":2,"toString":3,"fret":3}},{"positions":[-1,-1,3,5,6,-1],"baseFret":1},{"positions":[-1,8,10,10,-1,-1],"baseFret":8,"barre":{"fromString":3,"toString":4,"fret":10}}]}
{"name":"Bb6","variations":[{"positions":[1,3,-1,2,3,-1],"baseFret":1},{"positions":[-1,-1,3,5,3,5],"baseFret":1},{"positions":[-1,8,10,7,10,-1],"baseFret":7}]}
{"name":"Bb7","variations":[{"positions":[1,3,1,2,1,1],"baseFret":1,"barre":{"fromString":5,"toString":6,"fret":1}},{"positions":[1,3,-1,2,4,-1],"baseFret":1},{"positions":[-1,-1,3,5,4,5],"baseFret":1},{"positions":[-1,8,7,8,6,-1],"baseFret":6},{"positions":[-1,8,10,8,10,8],"baseFret":8},{"positions":[-1,8,10,10,10,11],"baseFret":8,"barre":{"fromString":3,"toString":5,"fret":10}}]}
{"name":"Bbmaj7","variations":[{"positions":[1,-1,2,2,1,-1],"baseFret":1,"barre":{"fromString":3,"toString":4,"fret":2}},{"positions":[-1,-1,3,5,5,5],"baseFret":1,"barre":{"fromString":4,"toString":6,"fret":5}},{"positions":[-1,8,7,5,5,5],"baseFret":5,"barre":{"fromString":4,"toString":6,"fret":5}},{"positions":[-1,8,10,9,10,8],"baseFret":8}]}
{"name":"Bb9","variations":[{"positions":[1,3,1,2,1,3],"baseFret":1},{"positions":[-1,8,7,8,8,8],"baseFret":7,"barre":{"fromString":4,"toString":6,"fret":8}}]}
{"name":"Bbmaj9","variations":[{"positions":[1,0,2,0,1,-1],"baseFret":1},{"positions":[-1,8,5,5,5,5],"baseFret":5,"barre":{"fromString":3,"toString":6,"fret":5}}]}
{"name":"Bb11","variations":[{"positions":[1,1,1,2,1,3],"baseFret":1,"barre":{"fromString":1,"toString":3,"fret":1}},{"positions":[-1,-1,3,3,4,5],"baseFret":1,"barre":{"fromString":3,"toString":4,"fret":3}},{"positions":[6,6,7,8,6,6],"baseFret":6,"barre":{"fromString":1,"toString":2,"fret":6}},{"positions":[-1,8,7,8,6,6],"baseFret":6,"barre":{"fromString":5,"toString":6,"fret":6}}]}
{"name":"Bb13","variations":[{"positions":[1,3,1,2,3,1],"baseFret":1},{"positions":[-1,8,7,8,8,10],"baseFret":7,"barre":{"fromString":4,"toString":5,"fret":8}}]}
{"name":"Bbmaj13","variations":[{"positions":[1,-1,2,2,3,-1],"baseFret":1,"barre":{"fromString":3,"toString":4,"fret":2}}]}
{"name":"Bbm","variations":[{"positions":[1,3,3,1,1,1],"baseFret":1,"barre":{"fromString":2,"toString":3,"fret":3}},{"positions":[-1,-1,3,5,6,4],"baseFret":1},{"positions":[-1,-1,6,5,6,4],"baseFret":4},{"positions":[-1,8,6,5,6,-1],"baseFret":5},{"positions":[-1,8,10,10,9,8],"baseFret":8,"barre":{"fromString":3,"toString":4,"fret":10}},{"positions":[-1,11,10,10,9,-1],"baseFret":9,"barre":{"fromString":3,"toString":4,"fret":10}}]}
{"name":"Bbm6","variations":[{"positions":[-1,-1,0,1,1,1],"baseFret":1,"barre":{"fromString":4,"toString":6,"fret":1}},{"positions":[-1,-1,3,5,3,4],"baseFret":1},{"positions":[-1,8,-1,7,9,8],"baseFret":7}]}
{"name":"Bbm7","variations":[{"positions":[1,3,3,1,4,1],"baseFret":1,"barre":{"fromString":2,"toString":3,"fret":3}},{"positions":[-1,8,6,5,4,-1],"baseFret":4},{"positions":[-1,-1,6,8,6,8],"baseFret":6},{"positions":[-1,8,10,8,9,8],"baseFret":8}]}
{"name":"Bbm9","variations":[{"positions":[1,-1,1,1,1,3],"baseFret":1,"barre":{"fromString":3,"toString":5,"fret":1}},{"positions":[-1,8,6,8,8,-1],"baseFret":6,"barre":{"fromString":4,"toString":5,"fret":8}}]}
{"name":"Bbm11","variations":[{"positions":[1,1,1,1,1,1],"baseFret":1,"barre":{"fromString":1,"toString":6,"fret":1}},{"positions":[-1,8,6,8,8,6],"baseFret":6,"barre":{"fromString":4,"toString":5,"fret":8}}]}
{"name":"Bbm13","variations":[{"positions":[1,3,1,1,3,1],"baseFret":1,"barre":{"fromString":3,"toString":4,"fret":1}},{"positions":[-1,8,6,8,8,10],"baseFret":6,"barre":{"fromString":4,"toString":5,"fret":8}}]}
{"name":"Bbm(maj7)","variations":[{"positions":[1,3,2,1,1,1],"baseFret":1,"barre":{"fromString":4,"toString":6,"fret":1}},{"positions":[-1,8,6,5,5,-1],"baseFret":5,"barre":{"fromString":4,"toString":5,"fret":5}}]}
{"name":"Bbsus2","variations":[{"positions":[-1,-1,3,0,1,1],"baseFret":1,"barre":{"fromString":5,"toString":6,"fret":1}},{"positions":[-1,-1,3,5,6,3],"baseFret":1},{"positions":[-1,8,5,5,6,-1],"baseFret":5,"barre":{"fromString":3,"toString":4,"fret":5}},{"positions":[-1,8,10,10,8,8],"baseFret":8,"barre":{"fromString":3,"toString":4,"fret":10}}]}
{"name":"Bbsus4","variations":[{"positions":[1,3,3,3,1,1],"baseFret":1,"barre":{"fromString":2,"toString":4,"fret":3}},{"positions":[-1,-1,3,5,6,6],"baseFret":1,"barre":{"fromString":5,"toString":6,"fret":6}},{"positions":[-1,8,8,10,11,8],"baseFret":8,"barre":{"fromString":2,"toString":3,"fret":8}},{"positions":[-1,-1,10,10,11,13],"baseFret":10,"barre":{"fromString":3,"toString":4,"fret":10}}]}
{"name":"Bbdim","variations":[{"positions":[-1,-1,3,4,3,4],"baseFret":1},{"positions":[-1,8,9,7,9,-1],"baseFret":7}]}
{"name":"Bbaug","variations":[{"positions":[-1,-1,3,2,2,1],"baseFret":1,"barre":{"fromString":4,"toString":5,"fret":2}},{"positions":[-1,4,-1,6,6,5],"baseFret":4,"barre":{"fromString":4,"toString":5,"fret":6}},{"positions":[-1,8,7,6,6,-1],"baseFret":6,"barre":{"fromString":4,"toString":5,"fret":6}},{"positions":[9,-1,11,10,10,-1],"baseFret":9,"barre":{"fromString":4,"toString":5,"fret":10}}]}
{"name":"Bb6/9","variations":[{"positions":[1,3,-1,2,3,3],"baseFret":1,"barre":{"fromString":5,"toString":6,"fret":3}},{"positions":[-1,5,5,5,6,5],"baseFret":5,"barre":{"fromString":2,"toString":4,"fret":5}},{"positions":[13,10,10,10,10,10],"baseFret":10,"barre":{"fromString":2,"toString":6,"fret":10}}]}
{"name":"Bb7sus4","variations":[{"positions":[1,3,1,3,1,1],"baseFret":1,"barre":{"fromString":5,"toString":6,"fret":1}},{"positions":[-1,8,10,8,11,-1],"baseFret":8}]}
{"name":"Bb7b5","variations":[{"positions":[1,-1,1,2,0,-1],"baseFret":1},{"positions":[-1,8,9,8,10,-1],"baseFret":8}]}
{"name":"Bb7b9","variations":[{"positions":[1,3,4,2,1,1],"baseFret":1,"barre":{"fromString":5,"toString":6,"fret":1}},{"positions":[1,3,1,2,1,2],"baseFret":1},{"positions":[-1,-1,3,2,4,2],"baseFret":1},{"positions":[-1,8,7,8,7,8],"baseFret":7},{"positions":[-1,8,7,8,7,-1],"baseFret":7}]}
{"name":"Bb9sus4","variations":[{"positions":[-1,3,3,3,4,3],"baseFret":1,"barre":{"fromString":2,"toString":4,"fret":3}},{"positions":[-1,8,-1,8,8,6],"baseFret":6,"barre":{"fromString":4,"toString":5,"fret":8}},{"positions":[-1,8,8,8,8,8],"baseFret":8,"barre":{"fromString":2,"toString":6,"fret":8}}]}
{"name":"Bbadd9","variations":[{"positions":[-1,-1,3,2,1,3],"baseFret":1},{"positions":[-1,-1,5,5,6,5],"baseFret":5,"barre":{"fromString":3,"toString":4,"fret":5}},{"positions":[8,-1,7,10,8,-1],"baseFret":7},{"positions":[-1,10,10,10,10,-1],"baseFret":10,"barre":{"fromString":2,"toString":5,"fret":10}}]}
{"name":"Bbaug9","variations":[{"positions":[1,-1,1,2,2,3],"baseFret":1,"barre":{"fromString":4,"toString":5,"fret":2}},{"positions":[-1,8,7,8,8,9],"baseFret":7,"barre":{"fromString":4,"toString":5,"fret":8}}]}
{"name":"B","variations":[{"positions":[2,4,4,3,2,2],"baseFret":1,"barre":{"fromString":2,"toString":3,"fret":4}},{"positions":[6,-1,4,6,7,-1],"baseFret":4},{"positions":[-1,-1,4,6,7,6],"baseFret":4},{"positions":[9,-1,8,6,7,-1],"baseFret":6},{"positions":[-1,9,8,6,7,6],"baseFret":6},{"positions":[-1,9,11,11,11,9],"baseFret":9,"barre":{"fromString":3,"toString":5,"fret":11}}]}
{"name":"B5","variations":[{"positions":[2,4,4,-1,-1,-1],"baseFret":1,"barre":{"fromString":2,"toString":3,"fret":4}},{"positions":[-1,-1,4,6,7,-1],"baseFret":4},{"positions":[-1,9,11,11,-1,-1],"baseFret":9,"barre":{"fromString":3,"toString":4,"fret":11}}]}
{"name":"B6","variations":[{"positions":[2,4,-1,3,4,-1],"baseFret":1},{"positions":[2,-1,1,3,2,-1],"baseFret":1},{"positions":[-1,9,11,8,11,-1],"baseFret":8},{"positions":[-1,9,11,11,11,11],"baseFret":9,"barre":{"fromString":3,"toString":6,"fret":11}}]}
{"name":"B7","variations":[{"positions":[-1,-1,4,3,2,0],"baseFret":1},{"positions":[2,4,2,3,2,2],"baseFret":1,"barre":{"fromString":5,"toString":6,"fret":2}},{"positions":[2,4,-1,3,5,-1],"baseFret":1},{"positions":[-1,-1,4,6,5,6],"baseFret":4},{"positions":[-1,9,11,11,11,12],"baseFret":9,"barre":{"fromString":3,"toString":5,"fret":11}},{"positions":[-1,9,11,9,11,9],"baseFret":9}]}
{"name":"Bmaj7","variations":[{"positions":[-1,-1,4,3,2,1],"baseFret":1},{"positions":[2,-1,3,3,2,-1],"baseFret":1,"barre":{"fromString":3,"toString":4,"fret":3}},{"positions":[-1,9,8,6,6,6],"baseFret":6,"barre":{"fromString":4,"toString":6,"fret":6}},{"positions":[-1,9,11,10,11,9],"baseFret":9}]}
{"name":"B9","variations":[{"positions":[-1,-1,4,3,5,4],"baseFret":1},{"positions":[-1,1,2,1,2,2],"baseFret":1,"barre":{"fromString":5,"toString":6,"fret":2}},{"positions":[-1,9,8,9,9,9],"baseFret":8,"barre":{"fromString":4,"toString":6,"fret":9}}]}
{"name":"Bmaj9","variations":[{"positions":[2,-1,3,3,-1,4],"baseFret":1,"barre":{"fromString":3,"toString":4,"fret":3}},{"positions":[-1,9,6,6,6,6],"baseFret":6,"barre":{"fromString":3,"toString":6,"fret":6}}]}
{"name":"B11","variations":[{"positions":[2,2,2,3,2,4],"baseFret":1,"barre":{"fromString":1,"toString":3,"fret":2}},{"positions":[-1,-1,4,4,5,6],"baseFret":4,"barre":{"fromString":3,"toString":4,"fret":4}},{"positions":[7,7,8,9,7,7],"baseFret":7,"barre":{"fromString":1,"toString":2,"fret":7}},{"positions":[-1,9,8,9,7,7],"baseFret":7,"barre":{"fromString":5,"toString":6,"fret":7}}]}
{"name":"B13","variations":[{"positions":[-1,-1,2,3,4,2],"baseFret":1},{"positions":[2,-1,2,3,4,4],"baseFret":1,"barre":{"fromString":5,"toString":6,"fret":4}},{"positions":[2,4,2,3,4,2],"baseFret":1}]}
{"name":"Bmaj13","variations":[{"positions":[2,1,1,1,2,1],"baseFret":1,"barre":{"fromString":2,"toString":4,"fret":1}},{"positions":[-1,9,-1,10,11,11],"baseFret":9,"barre":{"fromString":5,"toString":6,"fret":11}}]}
{"name":"Bm","variations":[{"positions":[2,4,4,2,2,2],"baseFret":1,"barre":{"fromString":2,"toString":3,"fret":4}},{"positions":[-1,-1,4,2,2,5],"baseFret":1,"barre":{"fromString":4,"toString":5,"fret":2}},{"positions":[5,-1,4,6,7,-1],"baseFret":4},{"positions":[-1,-1,4,6,7,5],"baseFret":4},{"positions":[-1,9,7,6,7,-1],"baseFret":6},{"positions":[-1,9,11,11,10,9],"baseFret":9,"barre":{"fromString":3,"toString":4,"fret":11}},{"positions":[-1,12,11,11,10,-1],"baseFret":10,"barre":{"fromString":3,"toString":4,"fret":11}}]}
{"name":"Bm6","variations":[{"positions":[2,-1,1,2,2,2],"baseFret":1,"barre":{"fromString":4,"toString":6,"fret":2}},{"positions":[-1,-1,4,6,4,5],"baseFret":4},{"positions":[-1,-1,7,8,7,9],"baseFret":7},{"positions":[-1,-1,11,11,10,11],"baseFret":10,"barre":{"fromString":3,"toString":4,"fret":11}}]}
{"name":"Bm7","variations":[{"positions":[2,-1,2,2,2,-1],"baseFret":1,"barre":{"fromString":3,"toString":5,"fret":2}},{"positions":[-1,-1,4,6,5,5],"baseFret":4,"barre":{"fromString":5,"toString":6,"fret":5}},{"positions":[-1,-1,7,9,7,9],"baseFret":7}]}
{"name":"Bm9","variations":[{"positions":[2,0,2,1,2,-1],"baseFret":1},{"positions":[-1,9,7,9,9,-1],"baseFret":7,"barre":{"fromString":4,"toString":5,"fret":9}}]}
{"name":"Bm11","variations":[{"positions":[2,2,2,2,2,2],"baseFret":1,"barre":{"fromString":1,"toString":6,"fret":2}},{"positions":[-1,9,9,9,10,9],"baseFret":9,"barre":{"fromString":2,"toString":4,"fret":9}}]}
{"name":"Bm13","variations":[{"positions":[2,4,2,2,4,2],"baseFret":1,"barre":{"fromString":3,"toString":4,"fret":2}},{"positions":[-1,9,-1,9,10,11],"baseFret":9}]}
{"name":"Bm(maj7)","variations":[{"positions":[2,4,3,2,2,2],"baseFret":1,"barre":{"fromString":4,"toString":6,"fret":2}},{"positions":[-1,-1,4,6,6,5],"baseFret":4,"barre":{"fromString":4,"toString":5,"fret":6}}]}
{"name":"Bsus2","variations":[{"positions":[2,-1,-1,1,2,2],"baseFret":1,"barre":{"fromString":5,"toString":6,"fret":2}},{"positions":[-1,-1,4,6,7,4],"baseFret":4},{"positions":[-1,9,6,6,7,-1],"baseFret":6,"barre":{"fromString":3,"toString":4,"fret":6}},{"positions":[-1,9,11,11,9,9],"baseFret":9,"barre":{"fromString":3,"toString":4,"fret":11}}]}
{"name":"Bsus4","variations":[{"positions":[2,4,4,4,2,2],"baseFret":1,"barre":{"fromString":2,"toString":4,"fret":4}},{"positions":[-1,-1,4,6,7,7],"baseFret":4,"barre":{"fromString":5,"toString":6,"fret":7}},{"positions":[-1,-1,9,6,7,9],"baseFret":6},{"positions":[-1,9,9,11,12,9],"baseFret":9,"barre":{"fromString":2,"toString":3,"fret":9}}]}
{"name":"Bdim","variations":[{"positions":[2,-1,1,2,1,-1],"baseFret":1},{"positions":[-1,6,7,5,7,-1],"baseFret":5}]}
{"name":"Baug","variations":[{"positions":[-1,-1,0,3,3,2],"baseFret":1,"barre":{"fromString":4,"toString":5,"fret":3}},{"positions":[-1,5,-1,7,7,6],"baseFret":5,"barre":{"fromString":4,"toString":5,"fret":7}},{"positions":[-1,9,8,7,7,-1],"baseFret":7,"barre":{"fromString":4,"toString":5,"fret":7}},{"positions":[10,-1,12,11,11,-1],"baseFret":10,"barre":{"fromString":4,"toString":5,"fret":11}}]}
{"name":"B6/9","variations":[{"positions":[2,1,1,1,2,2],"baseFret":1,"barre":{"fromString":2,"toString":4,"fret":1}},{"positions":[-1,4,4,3,4,4],"baseFret":1,"barre":{"fromString":2,"toString":3,"fret":4}},{"positions":[-1,9,8,8,9,9],"baseFret":8,"barre":{"fromString":3,"toString":4,"fret":8}}]}
{"name":"B7sus4","variations":[{"positions":[2,4,2,4,2,2],"baseFret":1,"barre":{"fromString":5,"toString":6,"fret":2}},{"positions":[-1,-1,4,6,5,7],"baseFret":4}]}
{"name":"B7b5","variations":[{"positions":[2,-1,2,3,1,-1],"baseFret":1},{"positions":[8,-1,8,9,7,-1],"baseFret":7}]}
{"name":"B7b9","variations":[{"positions":[2,4,5,3,2,2],"baseFret":1,"barre":{"fromString":5,"toString":6,"fret":2}},{"positions":[2,4,2,3,2,3],"baseFret":1},{"positions":[-1,-1,4,3,5,3],"baseFret":1},{"positions":[-1,9,8,9,8,9],"baseFret":8}]}
{"name":"B9sus4","variations":[{"positions":[-1,4,4,4,5,4],"baseFret":4,"barre":{"fromString":2,"toString":4,"fret":4}},{"positions":[-1,9,-1,9,9,7],"baseFret":7,"barre":{"fromString":4,"toString":5,"fret":9}},{"positions":[-1,9,9,9,9,9],"baseFret":9,"barre":{"fromString":2,"toString":6,"fret":9}}]}
{"name":"Badd9","variations":[{"positions":[-1,-1,4,3,2,4],"baseFret":1},{"positions":[-1,-1,6,6,7,6],"baseFret":6,"barre":{"fromString":3,"toString":4,"fret":6}},{"positions":[-1,9,8,6,9,6],"baseFret":6},{"positions":[-1,11,11,11,11,-1],"baseFret":11,"barre":{"fromString":2,"toString":5,"fret":11}}]}
{"name":"Baug9","variations":[{"positions":[2,-1,2,3,3,4],"baseFret":1,"barre":{"fromString":4,"toString":5,"fret":3}},{"positions":[-1,9,8,9,9,10],"baseFret":8,"barre":{"fromString":4,"toString":5,"fret":9}}]}
